{"domain": "ads.pubmatic.com", "post_body": "", "platform": "unknown", "referrer": "unknown", "uri": "/AdServer/js/user_sync.html?r=6343&predirect=http%3A%2F%2Fads.servebom.com%2Fpartner%3Fcd%3D6343%26svc%3Dus%26id%3D5%26uid%3D", "label": 1, "headers": {"host": "ads.pubmatic.com", "user-agent": "Mozilla/5.0 (X11; Ubuntu; Linux x86_64; rv:33.0) Gecko/20100101 Firefox/33.0", "accept": "text/html,application/xhtml+xml,application/xml;q=0.9,*/*;q=0.8", "accept-language": "en-US,en;q=0.5", "accept-encoding": "gzip, deflate", "referer": "http://www.tomshardware.co.uk/answers/id-2218632/intel-82579v-gigabit-network-connection.html", "cookie": "KRTBCOOKIE_22=488-pcv:1|uid:4229181461887093853&KRTB&14911-pcv:1|uid:4229181461887093853&KRTB&16087-pcv:1|uid:4229181461887093853; PUBMDCID=3; KTPCACOOKIE=YES; SyncRTB=1426201200%3A2%7C1426806000%3A3_7_21_71%7C1428184800%3A56; KADUSERCOOKIE=AA9F8574-88CE-4CA7-8DA8-102AB87B0342; KRTBCOOKIE_80=4031-CAESEGvqFjTcen3E2f1Y_4jzkCI&KRTB&13036-CAESEGvqFjTcen3E2f1Y_4jzkCI&KRTB&15671-CAESEGvqFjTcen3E2f1Y_4jzkCI&KRTB&15669-CAESEGvqFjTcen3E2f1Y_4jzkCI; KRTBCOOKIE_57=476-uid:5085756635903038849; KRTBCOOKIE_27=1216-uid:aab354f9-7595-4700-8442-72b19b55d3fc", "connection": "keep-alive"}, "timestamp": "2015-03-06_13-49-26-092605"}