[{"src": ["Location", "GPS Location"], "dst": "108", "process_name": "com.weather.Weather", "process_id": "2147", "log_time": "07-09 01:40:35.440", "message": "libcore.os.write(108) writing with tag 0x11 data[[{\"alarmVolume\":71.42857360839844,\"altitude\":0,\"ringtoneVolume\":71.42857360839844,\"timestamp\":149956]", "channel": "INTERNAL"}, {"src": ["Location", "GPS Location"], "dst": "90", "process_name": "com.weather.Weather", "process_id": "2147", "log_time": "07-09 01:40:35.588", "message": "libcore.os.write(90) writing with tag 0x11 data[<?xml version='1.0' encoding='utf-8' standalone='yes' ?>.<map>.<string name=\"SMART_RATINGS_STATUS\">{]", "channel": "INTERNAL"}, {"src": ["Location", "GPS Location"], "dst": "108", "process_name": "com.weather.Weather", "process_id": "2147", "log_time": "07-09 01:40:36.041", "message": "libcore.os.write(108) writing with tag 0x11 data[<?xml version='1.0' encoding='utf-8' standalone='yes' ?>.<map>.<string name=\"SMART_RATINGS_STATUS\">{]", "channel": "INTERNAL"}, {"src": ["Location", "GPS Location"], "dst": "90", "process_name": "com.weather.Weather", "process_id": "2147", "log_time": "07-09 01:40:43.901", "message": "libcore.os.write(90) writing with tag 0x11 data[<?xml version='1.0' encoding='utf-8' standalone='yes' ?>.<map>.<int name=\"airlock.userRandomNumber\" ]", "channel": "INTERNAL"}, {"src": ["Location", "GPS Location"], "dst": "90", "process_name": "com.weather.Weather", "process_id": "2147", "log_time": "07-09 01:40:43.947", "message": "libcore.os.write(90) writing with tag 0x11 data[pollencast&quot;},&quot;description&quot;:&quot;Displayshealthinformation.&quot;},&quot;isON&quot;:t]", "channel": "INTERNAL"}, {"src": ["Location", "GPS Location"], "dst": "90", "process_name": "com.weather.Weather", "process_id": "2147", "log_time": "07-09 01:40:43.971", "message": "libcore.os.write(90) writing with tag 0x11 data[&quot;:&quot;YES&quot;,&quot;feedbackButton&quot;:&quot;SEND FEEDBACK&quot;,&quot;negativeAnswerMess]", "channel": "INTERNAL"}, {"src": ["Location", "GPS Location"], "dst": "90", "process_name": "com.weather.Weather", "process_id": "2147", "log_time": "07-09 01:40:43.986", "message": "libcore.os.write(90) writing with tag 0x11 data[&quot;},{&quot;isON&quot;:true,&quot;name&quot;:&quot;headsupv2EditorialCalendar.No Event&quot;}],&q]", "channel": "INTERNAL"}, {"src": ["Location", "GPS Location"], "dst": "90", "process_name": "com.weather.Weather", "process_id": "2147", "log_time": "07-09 01:40:43.994", "message": "libcore.os.write(90) writing with tag 0x11 data[headsup.Tomorrow ForecastDynamic&quot;,&quot;type&quot;:&quot;FEATURE&quot;,&quot;source&quot;:&quot]", "channel": "INTERNAL"}, {"src": ["Location", "GPS Location"], "dst": "90", "process_name": "com.weather.Weather", "process_id": "2147", "log_time": "07-09 01:40:44.041", "message": "libcore.os.write(90) writing with tag 0x11 data[video.Video Autoplay CTA&quot;,&quot;type&quot;:&quot;FEATURE&quot;,&quot;source&quot;:&quot;SERVER&]", "channel": "INTERNAL"}, {"src": ["Location", "GPS Location"], "dst": "90", "process_name": "com.weather.Weather", "process_id": "2147", "log_time": "07-09 01:40:44.088", "message": "libcore.os.write(90) writing with tag 0x11 data[:{&quot;plat&quot;:&quot;wx_droid_phone&quot;,&quot;pos&quot;:&quot;top300&quot;,&quot;tile&quot;:&q]", "channel": "INTERNAL"}, {"src": ["Location", "GPS Location"], "dst": "90", "process_name": "com.weather.Weather", "process_id": "2147", "log_time": "07-09 01:40:44.158", "message": "libcore.os.write(90) writing with tag 0x11 data[&quot;fgeo&quot;:&quot;%%FGEO%%&quot;,&quot;tile&quot;:&quot;%%TILE%%&quot;,&quot;fhic&quot;:&quot;%]", "channel": "INTERNAL"}, {"src": ["Location", "GPS Location"], "dst": "90", "process_name": "com.weather.Weather", "process_id": "2147", "log_time": "07-09 01:40:44.174", "message": "libcore.os.write(90) writing with tag 0x11 data[&quot;,&quot;source&quot;:&quot;SERVER&quot;,&quot;configurationStatuses&quot;:[],&quot;sendToAnalyt]", "channel": "INTERNAL"}, {"src": ["Location", "GPS Location"], "dst": "90", "process_name": "com.weather.Weather", "process_id": "2147", "log_time": "07-09 01:40:44.244", "message": "libcore.os.write(90) writing with tag 0x11 data[<?xml version='1.0' encoding='utf-8' standalone='yes' ?>.<map>.<string name=\"inputFieldsForAnalytics]", "channel": "INTERNAL"}, {"src": ["Location", "GPS Location"], "dst": "90", "process_name": "com.weather.Weather", "process_id": "2147", "log_time": "07-09 01:40:44.276", "message": "libcore.os.write(90) writing with tag 0x11 data[pollencast&quot;},&quot;description&quot;:&quot;Displayshealthinformation.&quot;},&quot;isON&quot;:t]", "channel": "INTERNAL"}, {"src": ["Location", "GPS Location"], "dst": "90", "process_name": "com.weather.Weather", "process_id": "2147", "log_time": "07-09 01:40:44.307", "message": "libcore.os.write(90) writing with tag 0x11 data[&quot;:&quot;YES&quot;,&quot;feedbackButton&quot;:&quot;SEND FEEDBACK&quot;,&quot;negativeAnswerMess]", "channel": "INTERNAL"}, {"src": ["Location", "GPS Location"], "dst": "90", "process_name": "com.weather.Weather", "process_id": "2147", "log_time": "07-09 01:40:44.346", "message": "libcore.os.write(90) writing with tag 0x11 data[&quot;},{&quot;isON&quot;:true,&quot;name&quot;:&quot;headsupv2EditorialCalendar.No Event&quot;}],&q]", "channel": "INTERNAL"}, {"src": ["Location", "GPS Location"], "dst": "90", "process_name": "com.weather.Weather", "process_id": "2147", "log_time": "07-09 01:40:44.401", "message": "libcore.os.write(90) writing with tag 0x11 data[headsup.Tomorrow ForecastDynamic&quot;,&quot;type&quot;:&quot;FEATURE&quot;,&quot;source&quot;:&quot]", "channel": "INTERNAL"}, {"src": ["Location", "GPS Location"], "dst": "90", "process_name": "com.weather.Weather", "process_id": "2147", "log_time": "07-09 01:40:44.424", "message": "libcore.os.write(90) writing with tag 0x11 data[video.Video Autoplay CTA&quot;,&quot;type&quot;:&quot;FEATURE&quot;,&quot;source&quot;:&quot;SERVER&]", "channel": "INTERNAL"}, {"src": ["Location", "GPS Location"], "dst": "90", "process_name": "com.weather.Weather", "process_id": "2147", "log_time": "07-09 01:40:44.455", "message": "libcore.os.write(90) writing with tag 0x11 data[:{&quot;plat&quot;:&quot;wx_droid_phone&quot;,&quot;pos&quot;:&quot;top300&quot;,&quot;tile&quot;:&q]", "channel": "INTERNAL"}, {"src": ["Location", "GPS Location"], "dst": "90", "process_name": "com.weather.Weather", "process_id": "2147", "log_time": "07-09 01:40:44.486", "message": "libcore.os.write(90) writing with tag 0x11 data[&quot;fgeo&quot;:&quot;%%FGEO%%&quot;,&quot;tile&quot;:&quot;%%TILE%%&quot;,&quot;fhic&quot;:&quot;%]", "channel": "INTERNAL"}, {"src": ["Location", "GPS Location"], "dst": "90", "process_name": "com.weather.Weather", "process_id": "2147", "log_time": "07-09 01:40:44.502", "message": "libcore.os.write(90) writing with tag 0x11 data[&quot;,&quot;source&quot;:&quot;SERVER&quot;,&quot;configurationStatuses&quot;:[],&quot;sendToAnalyt]", "channel": "INTERNAL"}, {"src": ["Location", "GPS Location"], "dst": "90", "process_name": "com.weather.Weather", "process_id": "2147", "log_time": "07-09 01:40:44.596", "message": "libcore.os.write(90) writing with tag 0x11 data[<?xml version='1.0' encoding='utf-8' standalone='yes' ?>.<map>.<int name=\"airlock.userRandomNumber\" ]", "channel": "INTERNAL"}, {"src": ["Location", "GPS Location"], "dst": "90", "process_name": "com.weather.Weather", "process_id": "2147", "log_time": "07-09 01:40:44.627", "message": "libcore.os.write(90) writing with tag 0x11 data[pollencast&quot;},&quot;description&quot;:&quot;Displayshealthinformation.&quot;},&quot;isON&quot;:t]", "channel": "INTERNAL"}, {"src": ["Location", "GPS Location"], "dst": "90", "process_name": "com.weather.Weather", "process_id": "2147", "log_time": "07-09 01:40:44.658", "message": "libcore.os.write(90) writing with tag 0x11 data[&quot;:&quot;YES&quot;,&quot;feedbackButton&quot;:&quot;SEND FEEDBACK&quot;,&quot;negativeAnswerMess]", "channel": "INTERNAL"}, {"src": ["Location", "GPS Location"], "dst": "90", "process_name": "com.weather.Weather", "process_id": "2147", "log_time": "07-09 01:40:44.674", "message": "libcore.os.write(90) writing with tag 0x11 data[&quot;},{&quot;isON&quot;:true,&quot;name&quot;:&quot;headsupv2EditorialCalendar.No Event&quot;}],&q]", "channel": "INTERNAL"}, {"src": ["Location", "GPS Location"], "dst": "90", "process_name": "com.weather.Weather", "process_id": "2147", "log_time": "07-09 01:40:44.690", "message": "libcore.os.write(90) writing with tag 0x11 data[headsup.Tomorrow ForecastDynamic&quot;,&quot;type&quot;:&quot;FEATURE&quot;,&quot;source&quot;:&quot]", "channel": "INTERNAL"}, {"src": ["Location", "GPS Location"], "dst": "90", "process_name": "com.weather.Weather", "process_id": "2147", "log_time": "07-09 01:40:44.729", "message": "libcore.os.write(90) writing with tag 0x11 data[video.Video Autoplay CTA&quot;,&quot;type&quot;:&quot;FEATURE&quot;,&quot;source&quot;:&quot;SERVER&]", "channel": "INTERNAL"}, {"src": ["Location", "GPS Location"], "dst": "90", "process_name": "com.weather.Weather", "process_id": "2147", "log_time": "07-09 01:40:44.744", "message": "libcore.os.write(90) writing with tag 0x11 data[:{&quot;plat&quot;:&quot;wx_droid_phone&quot;,&quot;pos&quot;:&quot;top300&quot;,&quot;tile&quot;:&q]", "channel": "INTERNAL"}, {"src": ["Location", "GPS Location"], "dst": "90", "process_name": "com.weather.Weather", "process_id": "2147", "log_time": "07-09 01:40:44.768", "message": "libcore.os.write(90) writing with tag 0x11 data[&quot;fgeo&quot;:&quot;%%FGEO%%&quot;,&quot;tile&quot;:&quot;%%TILE%%&quot;,&quot;fhic&quot;:&quot;%]", "channel": "INTERNAL"}, {"src": ["Location", "GPS Location"], "dst": "90", "process_name": "com.weather.Weather", "process_id": "2147", "log_time": "07-09 01:40:44.807", "message": "libcore.os.write(90) writing with tag 0x11 data[&quot;,&quot;source&quot;:&quot;SERVER&quot;,&quot;configurationStatuses&quot;:[],&quot;sendToAnalyt]", "channel": "INTERNAL"}, {"src": ["Location", "GPS Location"], "dst": "90", "process_name": "com.weather.Weather", "process_id": "2147", "log_time": "07-09 01:40:47.010", "message": "libcore.os.write(90) writing with tag 0x11 data[<?xml version='1.0' encoding='utf-8' standalone='yes' ?>.<map>.<int name=\"airlock.userRandomNumber\" ]", "channel": "INTERNAL"}, {"src": ["Location", "GPS Location"], "dst": "90", "process_name": "com.weather.Weather", "process_id": "2147", "log_time": "07-09 01:40:47.033", "message": "libcore.os.write(90) writing with tag 0x11 data[&quot;,&quot;ch&quot;:&quot;pollencast&quot;},&quot;description&quot;:&quot;Displayshealthinformatio]", "channel": "INTERNAL"}, {"src": ["Location", "GPS Location"], "dst": "90", "process_name": "com.weather.Weather", "process_id": "2147", "log_time": "07-09 01:40:47.072", "message": "libcore.os.write(90) writing with tag 0x11 data[&quot;:&quot;Are you enjoying the The Weather Channel App?&quot;,&quot;emailSubject&quot;:&quot;Andr]", "channel": "INTERNAL"}, {"src": ["Location", "GPS Location"], "dst": "90", "process_name": "com.weather.Weather", "process_id": "2147", "log_time": "07-09 01:40:47.088", "message": "libcore.os.write(90) writing with tag 0x11 data[&quot;:&quot;headsupv2.Allergy&quot;,&quot;type&quot;:&quot;FEATURE&quot;,&quot;source&quot;:&quot;S]", "channel": "INTERNAL"}, {"src": ["Location", "GPS Location"], "dst": "90", "process_name": "com.weather.Weather", "process_id": "2147", "log_time": "07-09 01:40:47.111", "message": "libcore.os.write(90) writing with tag 0x11 data[&quot;configurationStatuses&quot;:[],&quot;sendToAnalytics&quot;:false},{&quot;isON&quot;:false,&quo]", "channel": "INTERNAL"}, {"src": ["Location", "GPS Location"], "dst": "90", "process_name": "com.weather.Weather", "process_id": "2147", "log_time": "07-09 01:40:47.119", "message": "libcore.os.write(90) writing with tag 0x11 data[&quot;320x80&quot;],&quot;slotName&quot;:&quot;weather.bb&quot;,&quot;adUnitSuffix&quot;:&quot;displ]", "channel": "INTERNAL"}, {"src": ["Location", "GPS Location"], "dst": "90", "process_name": "com.weather.Weather", "process_id": "2147", "log_time": "07-09 01:40:47.143", "message": "libcore.os.write(90) writing with tag 0x11 data[:&quot;top300&quot;,&quot;tile&quot;:&quot;1&quot;}},{&quot;sizes&quot;:[&quot;320x50&quot;,&quot;32]", "channel": "INTERNAL"}, {"src": ["Location", "GPS Location"], "dst": "90", "process_name": "com.weather.Weather", "process_id": "2147", "log_time": "07-09 01:40:47.158", "message": "libcore.os.write(90) writing with tag 0x11 data[output=xml_vast3&amp;c=%%ORD%%&amp;unviewed_position_start=1&amp;ad_rule=1&amp;description_url=http%]", "channel": "INTERNAL"}, {"src": ["Location", "NET-based Location"], "dst": "172.217.5.228", "process_name": "com.google.android.apps.genie.geniewidget", "process_id": "2087", "log_time": "07-09 01:40:47.174", "message": "libcore.os.send(172.217.5.228) received data with tag 0x21 data=[POST /m/appreq HTTP/1.1..Content-Type", "channel": "HTTP"}, {"src": ["Location", "GPS Location"], "dst": "90", "process_name": "com.weather.Weather", "process_id": "2147", "log_time": "07-09 01:40:47.182", "message": "libcore.os.write(90) writing with tag 0x11 data[name=\"airlock.default.language\">en</string>.<long name=\"airlock.lastCalculateTime\" value=\"1499564443]", "channel": "INTERNAL"}, {"src": ["Location", "GPS Location"], "dst": "90", "process_name": "com.weather.Weather", "process_id": "2147", "log_time": "07-09 01:40:47.229", "message": "libcore.os.write(90) writing with tag 0x11 data[<?xml version='1.0' encoding='utf-8' standalone='yes' ?>.<map>.<string name=\"inputFieldsForAnalytics]", "channel": "INTERNAL"}, {"src": ["Location", "GPS Location"], "dst": "90", "process_name": "com.weather.Weather", "process_id": "2147", "log_time": "07-09 01:40:47.252", "message": "libcore.os.write(90) writing with tag 0x11 data[&quot;,&quot;ch&quot;:&quot;pollencast&quot;},&quot;description&quot;:&quot;Displayshealthinformatio]", "channel": "INTERNAL"}, {"src": ["Location", "GPS Location"], "dst": "90", "process_name": "com.weather.Weather", "process_id": "2147", "log_time": "07-09 01:40:47.260", "message": "libcore.os.write(90) writing with tag 0x11 data[&quot;:&quot;Are you enjoying the The Weather Channel App?&quot;,&quot;emailSubject&quot;:&quot;Andr]", "channel": "INTERNAL"}, {"src": ["Location", "GPS Location"], "dst": "90", "process_name": "com.weather.Weather", "process_id": "2147", "log_time": "07-09 01:40:47.268", "message": "libcore.os.write(90) writing with tag 0x11 data[&quot;:&quot;headsupv2.Allergy&quot;,&quot;type&quot;:&quot;FEATURE&quot;,&quot;source&quot;:&quot;S]", "channel": "INTERNAL"}, {"src": ["Location", "GPS Location"], "dst": "90", "process_name": "com.weather.Weather", "process_id": "2147", "log_time": "07-09 01:40:47.291", "message": "libcore.os.write(90) writing with tag 0x11 data[&quot;configurationStatuses&quot;:[],&quot;sendToAnalytics&quot;:false},{&quot;isON&quot;:false,&quo]", "channel": "INTERNAL"}, {"src": ["Location", "GPS Location"], "dst": "90", "process_name": "com.weather.Weather", "process_id": "2147", "log_time": "07-09 01:40:47.307", "message": "libcore.os.write(90) writing with tag 0x11 data[&quot;320x80&quot;],&quot;slotName&quot;:&quot;weather.bb&quot;,&quot;adUnitSuffix&quot;:&quot;displ]", "channel": "INTERNAL"}, {"src": ["Location", "GPS Location"], "dst": "90", "process_name": "com.weather.Weather", "process_id": "2147", "log_time": "07-09 01:40:47.315", "message": "libcore.os.write(90) writing with tag 0x11 data[:&quot;top300&quot;,&quot;tile&quot;:&quot;1&quot;}},{&quot;sizes&quot;:[&quot;320x50&quot;,&quot;32]", "channel": "INTERNAL"}, {"src": ["Location", "GPS Location"], "dst": "90", "process_name": "com.weather.Weather", "process_id": "2147", "log_time": "07-09 01:40:47.330", "message": "libcore.os.write(90) writing with tag 0x11 data[output=xml_vast3&amp;c=%%ORD%%&amp;unviewed_position_start=1&amp;ad_rule=1&amp;description_url=http%]", "channel": "INTERNAL"}, {"src": ["Location", "GPS Location"], "dst": "90", "process_name": "com.weather.Weather", "process_id": "2147", "log_time": "07-09 01:40:47.338", "message": "libcore.os.write(90) writing with tag 0x11 data[name=\"airlock.lastCalculateTime\" value=\"1499564446974\" />.<string name=\"airlock.default.language\">en]", "channel": "INTERNAL"}, {"src": ["Location", "GPS Location"], "dst": "90", "process_name": "com.weather.Weather", "process_id": "2147", "log_time": "07-09 01:40:47.385", "message": "libcore.os.write(90) writing with tag 0x11 data[<?xml version='1.0' encoding='utf-8' standalone='yes' ?>.<map>.<int name=\"airlock.userRandomNumber\" ]", "channel": "INTERNAL"}, {"src": ["Location", "GPS Location"], "dst": "90", "process_name": "com.weather.Weather", "process_id": "2147", "log_time": "07-09 01:40:47.408", "message": "libcore.os.write(90) writing with tag 0x11 data[&quot;,&quot;ch&quot;:&quot;pollencast&quot;},&quot;description&quot;:&quot;Displayshealthinformatio]", "channel": "INTERNAL"}, {"src": ["Location", "GPS Location"], "dst": "90", "process_name": "com.weather.Weather", "process_id": "2147", "log_time": "07-09 01:40:47.416", "message": "libcore.os.write(90) writing with tag 0x11 data[&quot;:&quot;Are you enjoying the The Weather Channel App?&quot;,&quot;emailSubject&quot;:&quot;Andr]", "channel": "INTERNAL"}, {"src": ["Location", "GPS Location"], "dst": "90", "process_name": "com.weather.Weather", "process_id": "2147", "log_time": "07-09 01:40:47.440", "message": "libcore.os.write(90) writing with tag 0x11 data[&quot;:&quot;headsupv2.Allergy&quot;,&quot;type&quot;:&quot;FEATURE&quot;,&quot;source&quot;:&quot;S]", "channel": "INTERNAL"}, {"src": ["Location", "GPS Location"], "dst": "90", "process_name": "com.weather.Weather", "process_id": "2147", "log_time": "07-09 01:40:47.447", "message": "libcore.os.write(90) writing with tag 0x11 data[&quot;configurationStatuses&quot;:[],&quot;sendToAnalytics&quot;:false},{&quot;isON&quot;:false,&quo]", "channel": "INTERNAL"}, {"src": ["Location", "GPS Location"], "dst": "90", "process_name": "com.weather.Weather", "process_id": "2147", "log_time": "07-09 01:40:47.471", "message": "libcore.os.write(90) writing with tag 0x11 data[&quot;320x80&quot;],&quot;slotName&quot;:&quot;weather.bb&quot;,&quot;adUnitSuffix&quot;:&quot;displ]", "channel": "INTERNAL"}, {"src": ["Location", "GPS Location"], "dst": "90", "process_name": "com.weather.Weather", "process_id": "2147", "log_time": "07-09 01:40:47.479", "message": "libcore.os.write(90) writing with tag 0x11 data[:&quot;top300&quot;,&quot;tile&quot;:&quot;1&quot;}},{&quot;sizes&quot;:[&quot;320x50&quot;,&quot;32]", "channel": "INTERNAL"}, {"src": ["Location", "GPS Location"], "dst": "90", "process_name": "com.weather.Weather", "process_id": "2147", "log_time": "07-09 01:40:47.486", "message": "libcore.os.write(90) writing with tag 0x11 data[output=xml_vast3&amp;c=%%ORD%%&amp;unviewed_position_start=1&amp;ad_rule=1&amp;description_url=http%]", "channel": "INTERNAL"}, {"src": ["Location", "GPS Location"], "dst": "90", "process_name": "com.weather.Weather", "process_id": "2147", "log_time": "07-09 01:40:47.510", "message": "libcore.os.write(90) writing with tag 0x11 data[name=\"airlock.default.language\">en</string>.<long name=\"airlock.lastCalculateTime\" value=\"1499564446]", "channel": "INTERNAL"}, {"src": ["Location", "NET-based Location"], "dst": "172.217.5.228", "process_name": "com.google.android.apps.genie.geniewidget", "process_id": "2087", "log_time": "07-09 01:40:49.252", "message": "libcore.os.send(172.217.5.228) received data with tag 0x21 data=[POST /m/appreq HTTP/1.1..Content-Type", "channel": "HTTP"}, {"src": ["Location", "GPS Location"], "dst": "90", "process_name": "com.weather.Weather", "process_id": "2147", "log_time": "07-09 01:40:52.244", "message": "libcore.os.write(90) writing with tag 0x11 data[<?xml version='1.0' encoding='utf-8' standalone='yes' ?>.<map>.<int name=\"airlock.userRandomNumber\" ]", "channel": "INTERNAL"}, {"src": ["Location", "GPS Location"], "dst": "90", "process_name": "com.weather.Weather", "process_id": "2147", "log_time": "07-09 01:40:52.432", "message": "libcore.os.write(90) writing with tag 0x11 data[pollencast&quot;},&quot;description&quot;:&quot;Displayshealthinformation.&quot;},&quot;isON&quot;:t]", "channel": "INTERNAL"}, {"src": ["Location", "GPS Location"], "dst": "90", "process_name": "com.weather.Weather", "process_id": "2147", "log_time": "07-09 01:40:52.838", "message": "libcore.os.write(90) writing with tag 0x11 data[&quot;:&quot;YES&quot;,&quot;feedbackButton&quot;:&quot;SEND FEEDBACK&quot;,&quot;negativeAnswerMess]", "channel": "INTERNAL"}, {"src": ["Location", "GPS Location"], "dst": "90", "process_name": "com.weather.Weather", "process_id": "2147", "log_time": "07-09 01:40:52.861", "message": "libcore.os.write(90) writing with tag 0x11 data[&quot;},{&quot;isON&quot;:true,&quot;name&quot;:&quot;headsupv2EditorialCalendar.No Event&quot;}],&q]", "channel": "INTERNAL"}, {"src": ["Location", "GPS Location"], "dst": "90", "process_name": "com.weather.Weather", "process_id": "2147", "log_time": "07-09 01:40:52.908", "message": "libcore.os.write(90) writing with tag 0x11 data[headsup.Tomorrow ForecastDynamic&quot;,&quot;type&quot;:&quot;FEATURE&quot;,&quot;source&quot;:&quot]", "channel": "INTERNAL"}, {"src": ["Location", "GPS Location"], "dst": "90", "process_name": "com.weather.Weather", "process_id": "2147", "log_time": "07-09 01:40:52.924", "message": "libcore.os.write(90) writing with tag 0x11 data[video.Video Autoplay CTA&quot;,&quot;type&quot;:&quot;FEATURE&quot;,&quot;source&quot;:&quot;SERVER&]", "channel": "INTERNAL"}, {"src": ["Location", "GPS Location"], "dst": "90", "process_name": "com.weather.Weather", "process_id": "2147", "log_time": "07-09 01:40:52.947", "message": "libcore.os.write(90) writing with tag 0x11 data[:{&quot;plat&quot;:&quot;wx_droid_phone&quot;,&quot;pos&quot;:&quot;top300&quot;,&quot;tile&quot;:&q]", "channel": "INTERNAL"}, {"src": ["Location", "GPS Location"], "dst": "90", "process_name": "com.weather.Weather", "process_id": "2147", "log_time": "07-09 01:40:52.963", "message": "libcore.os.write(90) writing with tag 0x11 data[&quot;fgeo&quot;:&quot;%%FGEO%%&quot;,&quot;tile&quot;:&quot;%%TILE%%&quot;,&quot;fhic&quot;:&quot;%]", "channel": "INTERNAL"}, {"src": ["Location", "GPS Location"], "dst": "90", "process_name": "com.weather.Weather", "process_id": "2147", "log_time": "07-09 01:40:52.979", "message": "libcore.os.write(90) writing with tag 0x11 data[&quot;,&quot;source&quot;:&quot;SERVER&quot;,&quot;configurationStatuses&quot;:[],&quot;sendToAnalyt]", "channel": "INTERNAL"}, {"src": ["Location", "GPS Location"], "dst": "90", "process_name": "com.weather.Weather", "process_id": "2147", "log_time": "07-09 01:40:53.057", "message": "libcore.os.write(90) writing with tag 0x11 data[<?xml version='1.0' encoding='utf-8' standalone='yes' ?>.<map>.<string name=\"inputFieldsForAnalytics]", "channel": "INTERNAL"}, {"src": ["Location", "GPS Location"], "dst": "90", "process_name": "com.weather.Weather", "process_id": "2147", "log_time": "07-09 01:40:53.057", "message": "libcore.os.write(90) writing with tag 0x11 data[pollencast&quot;},&quot;description&quot;:&quot;Displayshealthinformation.&quot;},&quot;isON&quot;:t]", "channel": "INTERNAL"}, {"src": ["Location", "GPS Location"], "dst": "90", "process_name": "com.weather.Weather", "process_id": "2147", "log_time": "07-09 01:40:53.104", "message": "libcore.os.write(90) writing with tag 0x11 data[&quot;:&quot;YES&quot;,&quot;feedbackButton&quot;:&quot;SEND FEEDBACK&quot;,&quot;negativeAnswerMess]", "channel": "INTERNAL"}, {"src": ["Location", "GPS Location"], "dst": "90", "process_name": "com.weather.Weather", "process_id": "2147", "log_time": "07-09 01:40:53.127", "message": "libcore.os.write(90) writing with tag 0x11 data[&quot;},{&quot;isON&quot;:true,&quot;name&quot;:&quot;headsupv2EditorialCalendar.No Event&quot;}],&q]", "channel": "INTERNAL"}, {"src": ["Location", "GPS Location"], "dst": "90", "process_name": "com.weather.Weather", "process_id": "2147", "log_time": "07-09 01:40:53.151", "message": "libcore.os.write(90) writing with tag 0x11 data[headsup.Tomorrow ForecastDynamic&quot;,&quot;type&quot;:&quot;FEATURE&quot;,&quot;source&quot;:&quot]", "channel": "INTERNAL"}, {"src": ["Location", "GPS Location"], "dst": "90", "process_name": "com.weather.Weather", "process_id": "2147", "log_time": "07-09 01:40:53.166", "message": "libcore.os.write(90) writing with tag 0x11 data[video.Video Autoplay CTA&quot;,&quot;type&quot;:&quot;FEATURE&quot;,&quot;source&quot;:&quot;SERVER&]", "channel": "INTERNAL"}, {"src": ["Location", "GPS Location"], "dst": "90", "process_name": "com.weather.Weather", "process_id": "2147", "log_time": "07-09 01:40:53.182", "message": "libcore.os.write(90) writing with tag 0x11 data[:{&quot;plat&quot;:&quot;wx_droid_phone&quot;,&quot;pos&quot;:&quot;top300&quot;,&quot;tile&quot;:&q]", "channel": "INTERNAL"}, {"src": ["Location", "GPS Location"], "dst": "90", "process_name": "com.weather.Weather", "process_id": "2147", "log_time": "07-09 01:40:53.190", "message": "libcore.os.write(90) writing with tag 0x11 data[&quot;fgeo&quot;:&quot;%%FGEO%%&quot;,&quot;tile&quot;:&quot;%%TILE%%&quot;,&quot;fhic&quot;:&quot;%]", "channel": "INTERNAL"}, {"src": ["Location", "GPS Location"], "dst": "90", "process_name": "com.weather.Weather", "process_id": "2147", "log_time": "07-09 01:40:53.197", "message": "libcore.os.write(90) writing with tag 0x11 data[&quot;,&quot;source&quot;:&quot;SERVER&quot;,&quot;configurationStatuses&quot;:[],&quot;sendToAnalyt]", "channel": "INTERNAL"}, {"src": ["Location", "GPS Location"], "dst": "90", "process_name": "com.weather.Weather", "process_id": "2147", "log_time": "07-09 01:40:53.244", "message": "libcore.os.write(90) writing with tag 0x11 data[<?xml version='1.0' encoding='utf-8' standalone='yes' ?>.<map>.<int name=\"airlock.userRandomNumber\" ]", "channel": "INTERNAL"}, {"src": ["Location", "GPS Location"], "dst": "90", "process_name": "com.weather.Weather", "process_id": "2147", "log_time": "07-09 01:40:53.260", "message": "libcore.os.write(90) writing with tag 0x11 data[pollencast&quot;},&quot;description&quot;:&quot;Displayshealthinformation.&quot;},&quot;isON&quot;:t]", "channel": "INTERNAL"}, {"src": ["Location", "GPS Location"], "dst": "90", "process_name": "com.weather.Weather", "process_id": "2147", "log_time": "07-09 01:40:53.276", "message": "libcore.os.write(90) writing with tag 0x11 data[&quot;:&quot;YES&quot;,&quot;feedbackButton&quot;:&quot;SEND FEEDBACK&quot;,&quot;negativeAnswerMess]", "channel": "INTERNAL"}, {"src": ["Location", "GPS Location"], "dst": "90", "process_name": "com.weather.Weather", "process_id": "2147", "log_time": "07-09 01:40:53.291", "message": "libcore.os.write(90) writing with tag 0x11 data[&quot;},{&quot;isON&quot;:true,&quot;name&quot;:&quot;headsupv2EditorialCalendar.No Event&quot;}],&q]", "channel": "INTERNAL"}, {"src": ["Location", "NET-based Location"], "dst": "172.217.5.228", "process_name": "com.google.android.apps.genie.geniewidget", "process_id": "2087", "log_time": "07-09 01:40:53.315", "message": "libcore.os.send(172.217.5.228) received data with tag 0x21 data=[POST /m/appreq HTTP/1.1..Content-Type", "channel": "HTTP"}, {"src": ["Location", "GPS Location"], "dst": "90", "process_name": "com.weather.Weather", "process_id": "2147", "log_time": "07-09 01:40:53.315", "message": "libcore.os.write(90) writing with tag 0x11 data[headsup.Tomorrow ForecastDynamic&quot;,&quot;type&quot;:&quot;FEATURE&quot;,&quot;source&quot;:&quot]", "channel": "INTERNAL"}, {"src": ["Location", "GPS Location"], "dst": "90", "process_name": "com.weather.Weather", "process_id": "2147", "log_time": "07-09 01:40:53.330", "message": "libcore.os.write(90) writing with tag 0x11 data[video.Video Autoplay CTA&quot;,&quot;type&quot;:&quot;FEATURE&quot;,&quot;source&quot;:&quot;SERVER&]", "channel": "INTERNAL"}, {"src": ["Location", "GPS Location"], "dst": "90", "process_name": "com.weather.Weather", "process_id": "2147", "log_time": "07-09 01:40:53.338", "message": "libcore.os.write(90) writing with tag 0x11 data[:{&quot;plat&quot;:&quot;wx_droid_phone&quot;,&quot;pos&quot;:&quot;top300&quot;,&quot;tile&quot;:&q]", "channel": "INTERNAL"}, {"src": ["Location", "GPS Location"], "dst": "90", "process_name": "com.weather.Weather", "process_id": "2147", "log_time": "07-09 01:40:53.393", "message": "libcore.os.write(90) writing with tag 0x11 data[&quot;fgeo&quot;:&quot;%%FGEO%%&quot;,&quot;tile&quot;:&quot;%%TILE%%&quot;,&quot;fhic&quot;:&quot;%]", "channel": "INTERNAL"}, {"src": ["Location", "GPS Location"], "dst": "90", "process_name": "com.weather.Weather", "process_id": "2147", "log_time": "07-09 01:40:53.401", "message": "libcore.os.write(90) writing with tag 0x11 data[&quot;,&quot;source&quot;:&quot;SERVER&quot;,&quot;configurationStatuses&quot;:[],&quot;sendToAnalyt]", "channel": "INTERNAL"}, {"src": ["Location", "NET-based Location"], "dst": "172.217.5.228", "process_name": "com.google.android.apps.genie.geniewidget", "process_id": "2087", "log_time": "07-09 01:41:01.377", "message": "libcore.os.send(172.217.5.228) received data with tag 0x21 data=[POST /m/appreq HTTP/1.1..Content-Type", "channel": "HTTP"}, {"src": ["Location", "NET-based Location"], "dst": "172.217.5.228", "process_name": "com.google.android.apps.genie.geniewidget", "process_id": "2087", "log_time": "07-09 01:41:03.440", "message": "libcore.os.send(172.217.5.228) received data with tag 0x21 data=[POST /m/appreq HTTP/1.1..Content-Type", "channel": "HTTP"}, {"src": ["Location", "NET-based Location"], "dst": "172.217.5.228", "process_name": "com.google.android.apps.genie.geniewidget", "process_id": "2087", "log_time": "07-09 01:41:05.494", "message": "libcore.os.send(172.217.5.228) received data with tag 0x21 data=[POST /m/appreq HTTP/1.1..Content-Type", "channel": "HTTP"}, {"src": ["Location", "NET-based Location"], "dst": "172.217.5.228", "process_name": "com.google.android.apps.genie.geniewidget", "process_id": "2087", "log_time": "07-09 01:41:09.572", "message": "libcore.os.send(172.217.5.228) received data with tag 0x21 data=[POST /m/appreq HTTP/1.1..Content-Type", "channel": "HTTP"}, {"src": ["Location", "NET-based Location"], "dst": "172.217.5.228", "process_name": "com.google.android.apps.genie.geniewidget", "process_id": "2087", "log_time": "07-09 01:41:17.619", "message": "libcore.os.send(172.217.5.228) received data with tag 0x21 data=[POST /m/appreq HTTP/1.1..Content-Type", "channel": "HTTP"}]