<?xml version="1.0" ?><hierarchy>
  <node bounds="[0,0][720,1184]" checkable="false" checked="false" class="android.widget.FrameLayout" clickable="false" content-desc="" enabled="true" focusable="false" focused="false" index="0" long-clickable="false" package="com.atools.cuttherope" password="false" resource-id="NO_ID" scrollable="false" selected="false" text="">
    <node bounds="[0,0][720,1184]" checkable="false" checked="false" class="android.widget.LinearLayout" clickable="false" content-desc="" enabled="true" focusable="false" focused="false" index="0" long-clickable="false" package="com.atools.cuttherope" password="false" resource-id="NO_ID" scrollable="false" selected="false" text="">
      <node bounds="[0,50][720,100]" checkable="false" checked="false" class="android.widget.FrameLayout" clickable="false" content-desc="" enabled="true" focusable="false" focused="false" index="0" long-clickable="false" package="com.atools.cuttherope" password="false" resource-id="NO_ID" scrollable="false" selected="false" text="">
        <node bounds="[8,51][712,97]" checkable="false" checked="false" class="android.widget.TextView" clickable="false" content-desc="" enabled="true" focusable="false" focused="false" index="0" long-clickable="false" package="com.atools.cuttherope" password="false" resource-id="id/title" scrollable="false" selected="false" text="Cut The Rope Unlock"/>
      </node>
      <node bounds="[0,100][720,1184]" checkable="false" checked="false" class="android.widget.FrameLayout" clickable="false" content-desc="" enabled="true" focusable="false" focused="false" index="1" long-clickable="false" package="com.atools.cuttherope" password="false" resource-id="NO_ID" scrollable="false" selected="false" text="">
        <node bounds="[0,100][720,1184]" checkable="false" checked="false" class="android.widget.RelativeLayout" clickable="false" content-desc="" enabled="true" focusable="false" focused="false" index="0" long-clickable="false" package="com.atools.cuttherope" password="false" resource-id="NO_ID" scrollable="false" selected="false" text="">
          <node bounds="[0,100][720,403]" checkable="false" checked="false" class="android.widget.TextView" clickable="false" content-desc="" enabled="true" focusable="false" focused="false" index="0" long-clickable="false" package="com.atools.cuttherope" password="false" resource-id="id/text01" scrollable="false" selected="false" text="Welcome to Android's first Cut The Rope unlock app! This little tool will help you getting 3 stars on all 175 levels of Cut The Rope.  Requirements: 1. 'Cut The Rope' is installed. 2. Your device is ROOTED! 3. CTR started once but not running. "/>
          <node bounds="[219,411][501,507]" checkable="false" checked="false" class="android.widget.Button" clickable="true" content-desc="" enabled="true" focusable="true" focused="false" index="1" long-clickable="false" package="com.atools.cuttherope" password="false" resource-id="id/button1" scrollable="false" selected="false" text="解锁‘割绳子解锁器‘"/>
          <node bounds="[219,510][501,606]" checkable="false" checked="false" class="android.widget.Button" clickable="true" content-desc="" enabled="true" focusable="true" focused="false" index="2" long-clickable="false" package="com.atools.cuttherope" password="false" resource-id="id/button2" scrollable="false" selected="false" text="启动’割绳子解锁器‘"/>
          <node bounds="[0,618][720,622]" checkable="false" checked="false" class="android.view.View" clickable="false" content-desc="" enabled="true" focusable="false" focused="false" index="3" long-clickable="false" package="com.atools.cuttherope" password="false" resource-id="id/linie1" scrollable="false" selected="false" text=""/>
          <!--NAF: The following control may not be accessibility friendly-->
          <node NAF="true" bounds="[0,645][90,725]" checkable="false" checked="false" class="android.widget.ImageView" clickable="true" content-desc="" enabled="true" focusable="false" focused="false" index="4" long-clickable="false" package="com.atools.cuttherope" password="false" resource-id="id/imageFB" scrollable="false" selected="false" text=""/>
        </node>
      </node>
    </node>
  </node>
</hierarchy>