{"domain": "r1-ads.ace.advertising.com", "post_body": "", "platform": "unknown", "referrer": "unknown", "uri": "/ctst=1/site=796404/size=160600/u=2/bnum=17668826/hr=13/hl=0/c=2/scres=2/swh=640x480/tile=1/f=0/r=1/optn=1/fv=6/aolexp=1/dref=http%253A%252F%252Fwww.generalamuse.com%252Fgen.php?01AD=3SqsIUSjcBAdgKJad69Czr12_sHhukr1I7pzCDkenN5nDJxB6mKWIGw&01RI=BC579E72D628B4C&01NA=na", "label": "0", "headers": {"accept": "*/*", "referer": "http://www.generalamuse.com/gen.php", "accept-language": "en-us", "accept-encoding": "gzip, deflate", "user-agent": "Mozilla/4.0 (compatible; MSIE 6.0; Windows NT 5.1; SV1)", "host": "r1-ads.ace.advertising.com", "connection": "Keep-Alive", "cookie": "A07L=CT-1; ACID=Bz790013129729080012; ASCID=Bz790013129729080012"}, "timestamp": "2011-08-10_10-41-50-773682"}