[{"src": ["Location", "GPS Location", "NET-based Location"], "dst": "61", "process_name": "com.google.android.gms.persistent", "process_id": "8156", "log_time": "07-10 12:08:53.437", "message": "libcore.os.write(61) writing with tag 0x31 data[<?xml version='1.0' encoding='utf-8' standalone='yes' ?>.<map>.<long name=\"encryptionKey_3\" value=\"8]", "channel": "INTERNAL"}, {"src": ["Location", "GPS Location"], "dst": "114", "process_name": "com.weather.Weather", "process_id": "10697", "log_time": "07-10 12:08:54.180", "message": "libcore.os.write(114) writing with tag 0x11 data[<?xml version='1.0' encoding='utf-8' standalone='yes' ?>.<map>.<string name=\"ZOMBIE_WIDGET_LOCATIONS]", "channel": "INTERNAL"}, {"src": ["Location", "GPS Location"], "dst": "115", "process_name": "com.weather.Weather", "process_id": "10697", "log_time": "07-10 12:08:54.242", "message": "libcore.os.write(115) writing with tag 0x11 data[[{\"alarmVolume\":71.42857360839844,\"altitude\":65,\"ringtoneVolume\":57.14285659790039,\"batteryChargeSta]", "channel": "INTERNAL"}, {"src": ["Location", "GPS Location"], "dst": "104", "process_name": "com.weather.Weather", "process_id": "10697", "log_time": "07-10 12:08:54.250", "message": "libcore.os.write(104) writing with tag 0x11 data[<?xml version='1.0' encoding='utf-8' standalone='yes' ?>.<map>.<string name=\"CURRENT_LOCATION\">USCA0]", "channel": "INTERNAL"}, {"src": ["Location", "GPS Location"], "dst": "104", "process_name": "com.weather.Weather", "process_id": "10697", "log_time": "07-10 12:08:54.586", "message": "libcore.os.write(104) writing with tag 0x11 data[<?xml version='1.0' encoding='utf-8' standalone='yes' ?>.<map>.<string name=\"SMART_RATINGS_STATUS\">{]", "channel": "INTERNAL"}, {"src": ["Location", "GPS Location"], "dst": "88", "process_name": "com.weather.Weather", "process_id": "10697", "log_time": "07-10 12:08:54.656", "message": "libcore.os.write(88) writing with tag 0x11 data[<?xml version='1.0' encoding='utf-8' standalone='yes' ?>.<map>.<string name=\"SMART_RATINGS_STATUS\">{]", "channel": "INTERNAL"}, {"src": ["Location", "GPS Location"], "dst": "88", "process_name": "com.weather.Weather", "process_id": "10697", "log_time": "07-10 12:08:54.711", "message": "libcore.os.write(88) writing with tag 0x11 data[<?xml version='1.0' encoding='utf-8' standalone='yes' ?>.<map>.<string name=\"SMART_RATINGS_STATUS\">{]", "channel": "INTERNAL"}, {"src": ["Location", "GPS Location"], "dst": "88", "process_name": "com.weather.Weather", "process_id": "10697", "log_time": "07-10 12:08:54.742", "message": "libcore.os.write(88) writing with tag 0x11 data[<?xml version='1.0' encoding='utf-8' standalone='yes' ?>.<map>.<string name=\"SMART_RATINGS_STATUS\">{]", "channel": "INTERNAL"}, {"src": ["Location", "GPS Location"], "dst": "88", "process_name": "com.weather.Weather", "process_id": "10697", "log_time": "07-10 12:08:54.773", "message": "libcore.os.write(88) writing with tag 0x11 data[<?xml version='1.0' encoding='utf-8' standalone='yes' ?>.<map>.<string name=\"SMART_RATINGS_STATUS\">{]", "channel": "INTERNAL"}, {"src": ["Location", "GPS Location"], "dst": "54.239.28.123", "process_name": "com.weather.Weather", "process_id": "10697", "log_time": "07-10 12:08:55.008", "message": "SSLOutputStream.write(54.239.28.123) received data with tag 0x11 data=[POST /events_ANDROID_LocationUpdate HTTP/1.1..X-Amz-Date", "channel": "HTTPS"}, {"src": ["Location", "NET-based Location"], "dst": "61", "process_name": "com.google.android.gms.persistent", "process_id": "8156", "log_time": "07-10 12:08:55.461", "message": "libcore.os.write(61) writing with tag 0x21 data[<?xml version='1.0' encoding='utf-8' standalone='yes' ?>.<map>.<int name=\"apiLevel\" value=\"3\" />.</m]", "channel": "INTERNAL"}, {"src": ["Location", "GPS Location"], "dst": "101", "process_name": "com.weather.Weather", "process_id": "10697", "log_time": "07-10 12:08:56.852", "message": "libcore.os.write(101) writing with tag 0x11 data[<?xml version='1.0' encoding='utf-8' standalone='yes' ?>.<map>.<string name=\"SMART_RATINGS_STATUS\">{]", "channel": "INTERNAL"}, {"src": ["Location", "GPS Location"], "dst": "88", "process_name": "com.weather.Weather", "process_id": "10697", "log_time": "07-10 12:09:02.766", "message": "libcore.os.write(88) writing with tag 0x11 data[<?xml version='1.0' encoding='utf-8' standalone='yes' ?>.<map>.<string name=\"inputFieldsForAnalytics]", "channel": "INTERNAL"}, {"src": ["Location", "GPS Location"], "dst": "88", "process_name": "com.weather.Weather", "process_id": "10697", "log_time": "07-10 12:09:02.789", "message": "libcore.os.write(88) writing with tag 0x11 data[&quot;,&quot;ch&quot;:&quot;pollencast&quot;},&quot;description&quot;:&quot;Displayshealthinformatio]", "channel": "INTERNAL"}, {"src": ["Location", "GPS Location"], "dst": "88", "process_name": "com.weather.Weather", "process_id": "10697", "log_time": "07-10 12:09:02.805", "message": "libcore.os.write(88) writing with tag 0x11 data[&quot;:&quot;Are you enjoying the The Weather Channel App?&quot;,&quot;emailSubject&quot;:&quot;Andr]", "channel": "INTERNAL"}, {"src": ["Location", "GPS Location"], "dst": "88", "process_name": "com.weather.Weather", "process_id": "10697", "log_time": "07-10 12:09:02.812", "message": "libcore.os.write(88) writing with tag 0x11 data[&quot;:&quot;headsupv2.Allergy&quot;,&quot;type&quot;:&quot;FEATURE&quot;,&quot;source&quot;:&quot;S]", "channel": "INTERNAL"}, {"src": ["Location", "GPS Location"], "dst": "88", "process_name": "com.weather.Weather", "process_id": "10697", "log_time": "07-10 12:09:02.828", "message": "libcore.os.write(88) writing with tag 0x11 data[&quot;configurationStatuses&quot;:[],&quot;sendToAnalytics&quot;:false},{&quot;isON&quot;:false,&quo]", "channel": "INTERNAL"}, {"src": ["Location", "GPS Location"], "dst": "88", "process_name": "com.weather.Weather", "process_id": "10697", "log_time": "07-10 12:09:02.844", "message": "libcore.os.write(88) writing with tag 0x11 data[&quot;320x80&quot;],&quot;slotName&quot;:&quot;weather.bb&quot;,&quot;adUnitSuffix&quot;:&quot;displ]", "channel": "INTERNAL"}, {"src": ["Location", "GPS Location"], "dst": "88", "process_name": "com.weather.Weather", "process_id": "10697", "log_time": "07-10 12:09:02.859", "message": "libcore.os.write(88) writing with tag 0x11 data[:&quot;top300&quot;,&quot;tile&quot;:&quot;1&quot;}},{&quot;sizes&quot;:[&quot;320x50&quot;,&quot;32]", "channel": "INTERNAL"}, {"src": ["Location", "GPS Location"], "dst": "88", "process_name": "com.weather.Weather", "process_id": "10697", "log_time": "07-10 12:09:02.883", "message": "libcore.os.write(88) writing with tag 0x11 data[output=xml_vast3&amp;c=%%ORD%%&amp;unviewed_position_start=1&amp;ad_rule=1&amp;description_url=http%]", "channel": "INTERNAL"}, {"src": ["Location", "GPS Location"], "dst": "88", "process_name": "com.weather.Weather", "process_id": "10697", "log_time": "07-10 12:09:02.891", "message": "libcore.os.write(88) writing with tag 0x11 data[name=\"airlock.lastCalculateTime\" value=\"1499674711380\" />.<string name=\"airlock.default.language\">en]", "channel": "INTERNAL"}, {"src": ["Location", "GPS Location"], "dst": "88", "process_name": "com.weather.Weather", "process_id": "10697", "log_time": "07-10 12:09:02.945", "message": "libcore.os.write(88) writing with tag 0x11 data[<?xml version='1.0' encoding='utf-8' standalone='yes' ?>.<map>.<int name=\"airlock.userRandomNumber\" ]", "channel": "INTERNAL"}, {"src": ["Location", "GPS Location"], "dst": "88", "process_name": "com.weather.Weather", "process_id": "10697", "log_time": "07-10 12:09:02.977", "message": "libcore.os.write(88) writing with tag 0x11 data[&quot;,&quot;ch&quot;:&quot;pollencast&quot;},&quot;description&quot;:&quot;Displayshealthinformatio]", "channel": "INTERNAL"}, {"src": ["Location", "GPS Location"], "dst": "88", "process_name": "com.weather.Weather", "process_id": "10697", "log_time": "07-10 12:09:03.352", "message": "libcore.os.write(88) writing with tag 0x11 data[&quot;:&quot;Are you enjoying the The Weather Channel App?&quot;,&quot;emailSubject&quot;:&quot;Andr]", "channel": "INTERNAL"}, {"src": ["Location", "GPS Location"], "dst": "88", "process_name": "com.weather.Weather", "process_id": "10697", "log_time": "07-10 12:09:03.398", "message": "libcore.os.write(88) writing with tag 0x11 data[&quot;:&quot;headsupv2.Allergy&quot;,&quot;type&quot;:&quot;FEATURE&quot;,&quot;source&quot;:&quot;S]", "channel": "INTERNAL"}, {"src": ["Location", "GPS Location"], "dst": "88", "process_name": "com.weather.Weather", "process_id": "10697", "log_time": "07-10 12:09:03.437", "message": "libcore.os.write(88) writing with tag 0x11 data[&quot;configurationStatuses&quot;:[],&quot;sendToAnalytics&quot;:false},{&quot;isON&quot;:false,&quo]", "channel": "INTERNAL"}, {"src": ["Location", "GPS Location"], "dst": "88", "process_name": "com.weather.Weather", "process_id": "10697", "log_time": "07-10 12:09:03.461", "message": "libcore.os.write(88) writing with tag 0x11 data[&quot;320x80&quot;],&quot;slotName&quot;:&quot;weather.bb&quot;,&quot;adUnitSuffix&quot;:&quot;displ]", "channel": "INTERNAL"}, {"src": ["Location", "GPS Location"], "dst": "88", "process_name": "com.weather.Weather", "process_id": "10697", "log_time": "07-10 12:09:03.484", "message": "libcore.os.write(88) writing with tag 0x11 data[:&quot;top300&quot;,&quot;tile&quot;:&quot;1&quot;}},{&quot;sizes&quot;:[&quot;320x50&quot;,&quot;32]", "channel": "INTERNAL"}, {"src": ["Location", "GPS Location"], "dst": "88", "process_name": "com.weather.Weather", "process_id": "10697", "log_time": "07-10 12:09:03.516", "message": "libcore.os.write(88) writing with tag 0x11 data[output=xml_vast3&amp;c=%%ORD%%&amp;unviewed_position_start=1&amp;ad_rule=1&amp;description_url=http%]", "channel": "INTERNAL"}, {"src": ["Location", "GPS Location"], "dst": "88", "process_name": "com.weather.Weather", "process_id": "10697", "log_time": "07-10 12:09:03.539", "message": "libcore.os.write(88) writing with tag 0x11 data[name=\"airlock.default.language\">en</string>.<long name=\"airlock.lastCalculateTime\" value=\"1499688542]", "channel": "INTERNAL"}, {"src": ["Location", "GPS Location"], "dst": "88", "process_name": "com.weather.Weather", "process_id": "10697", "log_time": "07-10 12:09:03.617", "message": "libcore.os.write(88) writing with tag 0x11 data[<?xml version='1.0' encoding='utf-8' standalone='yes' ?>.<map>.<string name=\"inputFieldsForAnalytics]", "channel": "INTERNAL"}, {"src": ["Location", "GPS Location"], "dst": "88", "process_name": "com.weather.Weather", "process_id": "10697", "log_time": "07-10 12:09:03.648", "message": "libcore.os.write(88) writing with tag 0x11 data[&quot;,&quot;ch&quot;:&quot;pollencast&quot;},&quot;description&quot;:&quot;Displayshealthinformatio]", "channel": "INTERNAL"}, {"src": ["Location", "GPS Location"], "dst": "88", "process_name": "com.weather.Weather", "process_id": "10697", "log_time": "07-10 12:09:03.672", "message": "libcore.os.write(88) writing with tag 0x11 data[&quot;:&quot;Are you enjoying the The Weather Channel App?&quot;,&quot;emailSubject&quot;:&quot;Andr]", "channel": "INTERNAL"}, {"src": ["Location", "GPS Location"], "dst": "88", "process_name": "com.weather.Weather", "process_id": "10697", "log_time": "07-10 12:09:03.758", "message": "libcore.os.write(88) writing with tag 0x11 data[&quot;:&quot;headsupv2.Allergy&quot;,&quot;type&quot;:&quot;FEATURE&quot;,&quot;source&quot;:&quot;S]", "channel": "INTERNAL"}, {"src": ["Location", "GPS Location"], "dst": "88", "process_name": "com.weather.Weather", "process_id": "10697", "log_time": "07-10 12:09:03.820", "message": "libcore.os.write(88) writing with tag 0x11 data[&quot;configurationStatuses&quot;:[],&quot;sendToAnalytics&quot;:false},{&quot;isON&quot;:false,&quo]", "channel": "INTERNAL"}, {"src": ["Location", "GPS Location"], "dst": "88", "process_name": "com.weather.Weather", "process_id": "10697", "log_time": "07-10 12:09:03.852", "message": "libcore.os.write(88) writing with tag 0x11 data[&quot;320x80&quot;],&quot;slotName&quot;:&quot;weather.bb&quot;,&quot;adUnitSuffix&quot;:&quot;displ]", "channel": "INTERNAL"}, {"src": ["Location", "GPS Location"], "dst": "88", "process_name": "com.weather.Weather", "process_id": "10697", "log_time": "07-10 12:09:03.867", "message": "libcore.os.write(88) writing with tag 0x11 data[:&quot;top300&quot;,&quot;tile&quot;:&quot;1&quot;}},{&quot;sizes&quot;:[&quot;320x50&quot;,&quot;32]", "channel": "INTERNAL"}, {"src": ["Location", "GPS Location"], "dst": "88", "process_name": "com.weather.Weather", "process_id": "10697", "log_time": "07-10 12:09:03.898", "message": "libcore.os.write(88) writing with tag 0x11 data[output=xml_vast3&amp;c=%%ORD%%&amp;unviewed_position_start=1&amp;ad_rule=1&amp;description_url=http%]", "channel": "INTERNAL"}, {"src": ["Location", "GPS Location"], "dst": "88", "process_name": "com.weather.Weather", "process_id": "10697", "log_time": "07-10 12:09:03.953", "message": "libcore.os.write(88) writing with tag 0x11 data[name=\"airlock.lastCalculateTime\" value=\"1499688542758\" />.<string name=\"airlock.default.language\">en]", "channel": "INTERNAL"}, {"src": ["Location", "GPS Location"], "dst": "88", "process_name": "com.weather.Weather", "process_id": "10697", "log_time": "07-10 12:09:05.695", "message": "libcore.os.write(88) writing with tag 0x11 data[<?xml version='1.0' encoding='utf-8' standalone='yes' ?>.<map>.<string name=\"inputFieldsForAnalytics]", "channel": "INTERNAL"}, {"src": ["Location", "GPS Location"], "dst": "88", "process_name": "com.weather.Weather", "process_id": "10697", "log_time": "07-10 12:09:05.758", "message": "libcore.os.write(88) writing with tag 0x11 data[&quot;,&quot;ch&quot;:&quot;pollencast&quot;},&quot;description&quot;:&quot;Displayshealthinformatio]", "channel": "INTERNAL"}, {"src": ["Location", "GPS Location"], "dst": "88", "process_name": "com.weather.Weather", "process_id": "10697", "log_time": "07-10 12:09:05.773", "message": "libcore.os.write(88) writing with tag 0x11 data[&quot;:&quot;Are you enjoying the The Weather Channel App?&quot;,&quot;emailSubject&quot;:&quot;Andr]", "channel": "INTERNAL"}, {"src": ["Location", "GPS Location"], "dst": "88", "process_name": "com.weather.Weather", "process_id": "10697", "log_time": "07-10 12:09:05.789", "message": "libcore.os.write(88) writing with tag 0x11 data[&quot;:&quot;headsupv2.Allergy&quot;,&quot;type&quot;:&quot;FEATURE&quot;,&quot;source&quot;:&quot;S]", "channel": "INTERNAL"}, {"src": ["Location", "GPS Location"], "dst": "88", "process_name": "com.weather.Weather", "process_id": "10697", "log_time": "07-10 12:09:05.805", "message": "libcore.os.write(88) writing with tag 0x11 data[&quot;:false,&quot;fullName&quot;:&quot;headsup.Weekend ForecastDynamic&quot;,&quot;type&quot;:&quot]", "channel": "INTERNAL"}, {"src": ["Location", "GPS Location"], "dst": "88", "process_name": "com.weather.Weather", "process_id": "10697", "log_time": "07-10 12:09:05.812", "message": "libcore.os.write(88) writing with tag 0x11 data[videoVideoAutoplayCTA.Basic&quot;}],&quot;sendToAnalytics&quot;:false},{&quot;featureAttributes&quot]", "channel": "INTERNAL"}, {"src": ["Location", "GPS Location"], "dst": "88", "process_name": "com.weather.Weather", "process_id": "10697", "log_time": "07-10 12:09:05.820", "message": "libcore.os.write(88) writing with tag 0x11 data[&quot;:&quot;video.local&quot;,&quot;adUnitSuffix&quot;:&quot;video\\/local&quot;,&quot;parameters&qu]", "channel": "INTERNAL"}, {"src": ["Location", "GPS Location"], "dst": "88", "process_name": "com.weather.Weather", "process_id": "10697", "log_time": "07-10 12:09:05.828", "message": "libcore.os.write(88) writing with tag 0x11 data[https:\\/\\/pubads.g.doubleclick.net\\/gampad\\/ads?iu=%%AdUnitPrefix%%%%AdVideoUnitSuffix%%&amp;sz=640x]", "channel": "INTERNAL"}, {"src": ["Location", "GPS Location"], "dst": "88", "process_name": "com.weather.Weather", "process_id": "10697", "log_time": "07-10 12:09:05.836", "message": "libcore.os.write(88) writing with tag 0x11 data[&quot;SERVER&quot;,&quot;sendToAnalytics&quot;:false,&quot;isON&quot;:false}}</string>.<string name=]", "channel": "INTERNAL"}, {"src": ["Location", "GPS Location"], "dst": "88", "process_name": "com.weather.Weather", "process_id": "10697", "log_time": "07-10 12:09:05.859", "message": "libcore.os.write(88) writing with tag 0x11 data[<?xml version='1.0' encoding='utf-8' standalone='yes' ?>.<map>.<int name=\"airlock.userRandomNumber\" ]", "channel": "INTERNAL"}, {"src": ["Location", "GPS Location"], "dst": "88", "process_name": "com.weather.Weather", "process_id": "10697", "log_time": "07-10 12:09:05.891", "message": "libcore.os.write(88) writing with tag 0x11 data[&quot;,&quot;ch&quot;:&quot;pollencast&quot;},&quot;description&quot;:&quot;Displayshealthinformatio]", "channel": "INTERNAL"}, {"src": ["Location", "GPS Location"], "dst": "88", "process_name": "com.weather.Weather", "process_id": "10697", "log_time": "07-10 12:09:05.914", "message": "libcore.os.write(88) writing with tag 0x11 data[&quot;:&quot;Are you enjoying the The Weather Channel App?&quot;,&quot;emailSubject&quot;:&quot;Andr]", "channel": "INTERNAL"}, {"src": ["Location", "GPS Location"], "dst": "88", "process_name": "com.weather.Weather", "process_id": "10697", "log_time": "07-10 12:09:05.961", "message": "libcore.os.write(88) writing with tag 0x11 data[&quot;:&quot;headsupv2.Allergy&quot;,&quot;type&quot;:&quot;FEATURE&quot;,&quot;source&quot;:&quot;S]", "channel": "INTERNAL"}, {"src": ["Location", "GPS Location"], "dst": "88", "process_name": "com.weather.Weather", "process_id": "10697", "log_time": "07-10 12:09:05.977", "message": "libcore.os.write(88) writing with tag 0x11 data[&quot;:false,&quot;fullName&quot;:&quot;headsup.Weekend ForecastDynamic&quot;,&quot;type&quot;:&quot]", "channel": "INTERNAL"}, {"src": ["Location", "GPS Location"], "dst": "88", "process_name": "com.weather.Weather", "process_id": "10697", "log_time": "07-10 12:09:06.000", "message": "libcore.os.write(88) writing with tag 0x11 data[videoVideoAutoplayCTA.Basic&quot;}],&quot;sendToAnalytics&quot;:false},{&quot;featureAttributes&quot]", "channel": "INTERNAL"}, {"src": ["Location", "GPS Location"], "dst": "88", "process_name": "com.weather.Weather", "process_id": "10697", "log_time": "07-10 12:09:06.023", "message": "libcore.os.write(88) writing with tag 0x11 data[&quot;:&quot;video.local&quot;,&quot;adUnitSuffix&quot;:&quot;video\\/local&quot;,&quot;parameters&qu]", "channel": "INTERNAL"}, {"src": ["Location", "GPS Location"], "dst": "88", "process_name": "com.weather.Weather", "process_id": "10697", "log_time": "07-10 12:09:06.023", "message": "libcore.os.write(88) writing with tag 0x11 data[https:\\/\\/pubads.g.doubleclick.net\\/gampad\\/ads?iu=%%AdUnitPrefix%%%%AdVideoUnitSuffix%%&amp;sz=640x]", "channel": "INTERNAL"}, {"src": ["Location", "GPS Location"], "dst": "88", "process_name": "com.weather.Weather", "process_id": "10697", "log_time": "07-10 12:09:06.039", "message": "libcore.os.write(88) writing with tag 0x11 data[&quot;SERVER&quot;,&quot;sendToAnalytics&quot;:false,&quot;isON&quot;:false}}</string>.<string name=]", "channel": "INTERNAL"}, {"src": ["Location", "GPS Location"], "dst": "88", "process_name": "com.weather.Weather", "process_id": "10697", "log_time": "07-10 12:09:06.078", "message": "libcore.os.write(88) writing with tag 0x11 data[<?xml version='1.0' encoding='utf-8' standalone='yes' ?>.<map>.<string name=\"inputFieldsForAnalytics]", "channel": "INTERNAL"}, {"src": ["Location", "GPS Location"], "dst": "88", "process_name": "com.weather.Weather", "process_id": "10697", "log_time": "07-10 12:09:06.086", "message": "libcore.os.write(88) writing with tag 0x11 data[&quot;,&quot;ch&quot;:&quot;pollencast&quot;},&quot;description&quot;:&quot;Displayshealthinformatio]", "channel": "INTERNAL"}, {"src": ["Location", "GPS Location"], "dst": "88", "process_name": "com.weather.Weather", "process_id": "10697", "log_time": "07-10 12:09:06.094", "message": "libcore.os.write(88) writing with tag 0x11 data[&quot;:&quot;Are you enjoying the The Weather Channel App?&quot;,&quot;emailSubject&quot;:&quot;Andr]", "channel": "INTERNAL"}, {"src": ["Location", "GPS Location"], "dst": "88", "process_name": "com.weather.Weather", "process_id": "10697", "log_time": "07-10 12:09:06.109", "message": "libcore.os.write(88) writing with tag 0x11 data[&quot;:&quot;headsupv2.Allergy&quot;,&quot;type&quot;:&quot;FEATURE&quot;,&quot;source&quot;:&quot;S]", "channel": "INTERNAL"}, {"src": ["Location", "GPS Location"], "dst": "88", "process_name": "com.weather.Weather", "process_id": "10697", "log_time": "07-10 12:09:06.141", "message": "libcore.os.write(88) writing with tag 0x11 data[&quot;:false,&quot;fullName&quot;:&quot;headsup.Weekend ForecastDynamic&quot;,&quot;type&quot;:&quot]", "channel": "INTERNAL"}, {"src": ["Location", "GPS Location"], "dst": "88", "process_name": "com.weather.Weather", "process_id": "10697", "log_time": "07-10 12:09:06.148", "message": "libcore.os.write(88) writing with tag 0x11 data[videoVideoAutoplayCTA.Basic&quot;}],&quot;sendToAnalytics&quot;:false},{&quot;featureAttributes&quot]", "channel": "INTERNAL"}, {"src": ["Location", "GPS Location"], "dst": "88", "process_name": "com.weather.Weather", "process_id": "10697", "log_time": "07-10 12:09:06.164", "message": "libcore.os.write(88) writing with tag 0x11 data[&quot;:&quot;video.local&quot;,&quot;adUnitSuffix&quot;:&quot;video\\/local&quot;,&quot;parameters&qu]", "channel": "INTERNAL"}, {"src": ["Location", "GPS Location"], "dst": "88", "process_name": "com.weather.Weather", "process_id": "10697", "log_time": "07-10 12:09:06.180", "message": "libcore.os.write(88) writing with tag 0x11 data[https:\\/\\/pubads.g.doubleclick.net\\/gampad\\/ads?iu=%%AdUnitPrefix%%%%AdVideoUnitSuffix%%&amp;sz=640x]", "channel": "INTERNAL"}, {"src": ["Location", "GPS Location"], "dst": "88", "process_name": "com.weather.Weather", "process_id": "10697", "log_time": "07-10 12:09:06.180", "message": "libcore.os.write(88) writing with tag 0x11 data[&quot;SERVER&quot;,&quot;sendToAnalytics&quot;:false,&quot;isON&quot;:false}}</string>.<string name=]", "channel": "INTERNAL"}, {"src": ["Location", "GPS Location"], "dst": "88", "process_name": "com.weather.Weather", "process_id": "10697", "log_time": "07-10 12:09:10.625", "message": "libcore.os.write(88) writing with tag 0x11 data[<?xml version='1.0' encoding='utf-8' standalone='yes' ?>.<map>.<string name=\"inputFieldsForAnalytics]", "channel": "INTERNAL"}, {"src": ["Location", "GPS Location"], "dst": "88", "process_name": "com.weather.Weather", "process_id": "10697", "log_time": "07-10 12:09:10.734", "message": "libcore.os.write(88) writing with tag 0x11 data[pollencast&quot;},&quot;description&quot;:&quot;Displayshealthinformation.&quot;},&quot;isON&quot;:t]", "channel": "INTERNAL"}, {"src": ["Location", "GPS Location"], "dst": "88", "process_name": "com.weather.Weather", "process_id": "10697", "log_time": "07-10 12:09:10.742", "message": "libcore.os.write(88) writing with tag 0x11 data[&quot;:&quot;YES&quot;,&quot;feedbackButton&quot;:&quot;SEND FEEDBACK&quot;,&quot;negativeAnswerMess]", "channel": "INTERNAL"}, {"src": ["Location", "GPS Location"], "dst": "88", "process_name": "com.weather.Weather", "process_id": "10697", "log_time": "07-10 12:09:10.750", "message": "libcore.os.write(88) writing with tag 0x11 data[headsupv2.Allergy&quot;,&quot;type&quot;:&quot;FEATURE&quot;,&quot;source&quot;:&quot;SERVER&quot;,&]", "channel": "INTERNAL"}, {"src": ["Location", "GPS Location"], "dst": "88", "process_name": "com.weather.Weather", "process_id": "10697", "log_time": "07-10 12:09:10.883", "message": "libcore.os.write(88) writing with tag 0x11 data[sendToAnalytics&quot;:false},{&quot;isON&quot;:false,&quot;fullName&quot;:&quot;headsup.Sunrise Suns]", "channel": "INTERNAL"}, {"src": ["Location", "GPS Location"], "dst": "88", "process_name": "com.weather.Weather", "process_id": "10697", "log_time": "07-10 12:09:10.914", "message": "libcore.os.write(88) writing with tag 0x11 data[:&quot;weather.cc&quot;,&quot;adUnitSuffix&quot;:&quot;display\\/feed\\/feed_0&quot;,&quot;parameters&]", "channel": "INTERNAL"}, {"src": ["Location", "GPS Location"], "dst": "88", "process_name": "com.weather.Weather", "process_id": "10697", "log_time": "07-10 12:09:10.922", "message": "libcore.os.write(88) writing with tag 0x11 data[&quot;pos&quot;:&quot;top300&quot;,&quot;tile&quot;:&quot;1&quot;}},{&quot;sizes&quot;:[&quot;320x50]", "channel": "INTERNAL"}, {"src": ["Location", "GPS Location"], "dst": "88", "process_name": "com.weather.Weather", "process_id": "10697", "log_time": "07-10 12:09:10.930", "message": "libcore.os.write(88) writing with tag 0x11 data[cust_params=cnd%3D%%CONDITION%%%26sev%3D%%SEVERE%%%26ftl%3D%%FTL%%%26hlzip%3D%%HLZIP%%%26tmp%3D%%TMP]", "channel": "INTERNAL"}, {"src": ["Location", "GPS Location"], "dst": "88", "process_name": "com.weather.Weather", "process_id": "10697", "log_time": "07-10 12:09:10.930", "message": "libcore.os.write(88) writing with tag 0x11 data[ name=\"airlock.seasonId\">6f8cba0d-8e46-4c6b-8b70-9bac3cc5a085</string>.<string name=\"airlock.cached.]", "channel": "INTERNAL"}, {"src": ["Location", "GPS Location"], "dst": "88", "process_name": "com.weather.Weather", "process_id": "10697", "log_time": "07-10 12:09:11.016", "message": "libcore.os.write(88) writing with tag 0x11 data[<?xml version='1.0' encoding='utf-8' standalone='yes' ?>.<map>.<int name=\"airlock.userRandomNumber\" ]", "channel": "INTERNAL"}, {"src": ["Location", "GPS Location"], "dst": "88", "process_name": "com.weather.Weather", "process_id": "10697", "log_time": "07-10 12:09:11.039", "message": "libcore.os.write(88) writing with tag 0x11 data[pollencast&quot;},&quot;description&quot;:&quot;Displayshealthinformation.&quot;},&quot;isON&quot;:t]", "channel": "INTERNAL"}, {"src": ["Location", "GPS Location"], "dst": "88", "process_name": "com.weather.Weather", "process_id": "10697", "log_time": "07-10 12:09:11.047", "message": "libcore.os.write(88) writing with tag 0x11 data[&quot;:&quot;YES&quot;,&quot;feedbackButton&quot;:&quot;SEND FEEDBACK&quot;,&quot;negativeAnswerMess]", "channel": "INTERNAL"}, {"src": ["Location", "GPS Location"], "dst": "88", "process_name": "com.weather.Weather", "process_id": "10697", "log_time": "07-10 12:09:11.141", "message": "libcore.os.write(88) writing with tag 0x11 data[headsupv2.Allergy&quot;,&quot;type&quot;:&quot;FEATURE&quot;,&quot;source&quot;:&quot;SERVER&quot;,&]", "channel": "INTERNAL"}, {"src": ["Location", "GPS Location"], "dst": "88", "process_name": "com.weather.Weather", "process_id": "10697", "log_time": "07-10 12:09:11.148", "message": "libcore.os.write(88) writing with tag 0x11 data[sendToAnalytics&quot;:false},{&quot;isON&quot;:false,&quot;fullName&quot;:&quot;headsup.Sunrise Suns]", "channel": "INTERNAL"}, {"src": ["Location", "GPS Location"], "dst": "88", "process_name": "com.weather.Weather", "process_id": "10697", "log_time": "07-10 12:09:11.156", "message": "libcore.os.write(88) writing with tag 0x11 data[:&quot;weather.cc&quot;,&quot;adUnitSuffix&quot;:&quot;display\\/feed\\/feed_0&quot;,&quot;parameters&]", "channel": "INTERNAL"}, {"src": ["Location", "GPS Location"], "dst": "88", "process_name": "com.weather.Weather", "process_id": "10697", "log_time": "07-10 12:09:11.164", "message": "libcore.os.write(88) writing with tag 0x11 data[&quot;pos&quot;:&quot;top300&quot;,&quot;tile&quot;:&quot;1&quot;}},{&quot;sizes&quot;:[&quot;320x50]", "channel": "INTERNAL"}, {"src": ["Location", "GPS Location"], "dst": "88", "process_name": "com.weather.Weather", "process_id": "10697", "log_time": "07-10 12:09:11.172", "message": "libcore.os.write(88) writing with tag 0x11 data[cust_params=cnd%3D%%CONDITION%%%26sev%3D%%SEVERE%%%26ftl%3D%%FTL%%%26hlzip%3D%%HLZIP%%%26tmp%3D%%TMP]", "channel": "INTERNAL"}, {"src": ["Location", "GPS Location"], "dst": "88", "process_name": "com.weather.Weather", "process_id": "10697", "log_time": "07-10 12:09:11.180", "message": "libcore.os.write(88) writing with tag 0x11 data[airlock.direct.s3Path\">https://s3.amazonaws.com/airlockprod/PROD1/</string>.<string name=\"airlock.ca]", "channel": "INTERNAL"}, {"src": ["Location", "GPS Location"], "dst": "88", "process_name": "com.weather.Weather", "process_id": "10697", "log_time": "07-10 12:09:11.219", "message": "libcore.os.write(88) writing with tag 0x11 data[<?xml version='1.0' encoding='utf-8' standalone='yes' ?>.<map>.<string name=\"inputFieldsForAnalytics]", "channel": "INTERNAL"}, {"src": ["Location", "GPS Location"], "dst": "88", "process_name": "com.weather.Weather", "process_id": "10697", "log_time": "07-10 12:09:11.234", "message": "libcore.os.write(88) writing with tag 0x11 data[pollencast&quot;},&quot;description&quot;:&quot;Displayshealthinformation.&quot;},&quot;isON&quot;:t]", "channel": "INTERNAL"}, {"src": ["Location", "GPS Location"], "dst": "88", "process_name": "com.weather.Weather", "process_id": "10697", "log_time": "07-10 12:09:11.250", "message": "libcore.os.write(88) writing with tag 0x11 data[&quot;:&quot;YES&quot;,&quot;feedbackButton&quot;:&quot;SEND FEEDBACK&quot;,&quot;negativeAnswerMess]", "channel": "INTERNAL"}, {"src": ["Location", "GPS Location"], "dst": "88", "process_name": "com.weather.Weather", "process_id": "10697", "log_time": "07-10 12:09:11.352", "message": "libcore.os.write(88) writing with tag 0x11 data[headsupv2.Allergy&quot;,&quot;type&quot;:&quot;FEATURE&quot;,&quot;source&quot;:&quot;SERVER&quot;,&]", "channel": "INTERNAL"}, {"src": ["Location", "GPS Location"], "dst": "88", "process_name": "com.weather.Weather", "process_id": "10697", "log_time": "07-10 12:09:11.367", "message": "libcore.os.write(88) writing with tag 0x11 data[sendToAnalytics&quot;:false},{&quot;isON&quot;:false,&quot;fullName&quot;:&quot;headsup.Sunrise Suns]", "channel": "INTERNAL"}, {"src": ["Location", "GPS Location"], "dst": "88", "process_name": "com.weather.Weather", "process_id": "10697", "log_time": "07-10 12:09:11.383", "message": "libcore.os.write(88) writing with tag 0x11 data[:&quot;weather.cc&quot;,&quot;adUnitSuffix&quot;:&quot;display\\/feed\\/feed_0&quot;,&quot;parameters&]", "channel": "INTERNAL"}, {"src": ["Location", "GPS Location"], "dst": "88", "process_name": "com.weather.Weather", "process_id": "10697", "log_time": "07-10 12:09:11.391", "message": "libcore.os.write(88) writing with tag 0x11 data[&quot;pos&quot;:&quot;top300&quot;,&quot;tile&quot;:&quot;1&quot;}},{&quot;sizes&quot;:[&quot;320x50]", "channel": "INTERNAL"}, {"src": ["Location", "GPS Location"], "dst": "88", "process_name": "com.weather.Weather", "process_id": "10697", "log_time": "07-10 12:09:11.398", "message": "libcore.os.write(88) writing with tag 0x11 data[cust_params=cnd%3D%%CONDITION%%%26sev%3D%%SEVERE%%%26ftl%3D%%FTL%%%26hlzip%3D%%HLZIP%%%26tmp%3D%%TMP]", "channel": "INTERNAL"}, {"src": ["Location", "GPS Location"], "dst": "88", "process_name": "com.weather.Weather", "process_id": "10697", "log_time": "07-10 12:09:11.406", "message": "libcore.os.write(88) writing with tag 0x11 data[ name=\"airlock.seasonId\">6f8cba0d-8e46-4c6b-8b70-9bac3cc5a085</string>.<string name=\"airlock.cached.]", "channel": "INTERNAL"}]