[{"src": ["Location", "GPS Location"], "dst": "90", "process_name": "com.weather.Weather", "process_id": "827", "log_time": "07-09 19:51:59.777", "message": "libcore.os.write(90) writing with tag 0x11 data[[{\"alarmVolume\":71.42857360839844,\"altitude\":0,\"ringtoneVolume\":57.14285659790039,\"batteryChargeStar]", "channel": "INTERNAL"}, {"src": ["Location", "GPS Location"], "dst": "90", "process_name": "com.weather.Weather", "process_id": "827", "log_time": "07-09 19:51:59.793", "message": "libcore.os.write(90) writing with tag 0x11 data[<?xml version='1.0' encoding='utf-8' standalone='yes' ?>.<map>.<string name=\"SMART_RATINGS_STATUS\">{]", "channel": "INTERNAL"}, {"src": ["IMEI"], "dst": "92.242.140.21", "process_name": "ru.install.opera", "process_id": "2553", "log_time": "07-09 19:51:59.855", "message": "libcore.os.send(92.242.140.21) received data with tag 0x400 data=[GET /reg.php?country=us&phone=15306013355&op=AT&T@&balance=0&imei=351565054929465 HTTP/1.1..Host", "channel": "HTTP"}, {"src": ["IMEI"], "dst": "92.242.140.21", "process_name": "ru.install.opera", "process_id": "2553", "log_time": "07-09 19:51:59.863", "message": "libcore.os.send(92.242.140.21) received data with tag 0x400 data=[GET /getTask.php?imei=351565054929465&balance=0 HTTP/1.1..Host", "channel": "HTTP"}, {"src": ["Location", "GPS Location"], "dst": "86", "process_name": "com.weather.Weather", "process_id": "827", "log_time": "07-09 19:52:00.379", "message": "libcore.os.write(86) writing with tag 0x11 data[<?xml version='1.0' encoding='utf-8' standalone='yes' ?>.<map>.<string name=\"SMART_RATINGS_STATUS\">{]", "channel": "INTERNAL"}, {"src": ["Location", "GPS Location"], "dst": "86", "process_name": "com.weather.Weather", "process_id": "827", "log_time": "07-09 19:52:00.566", "message": "libcore.os.write(86) writing with tag 0x11 data[<?xml version='1.0' encoding='utf-8' standalone='yes' ?>.<map>.<string name=\"SMART_RATINGS_STATUS\">{]", "channel": "INTERNAL"}, {"src": ["Location", "GPS Location"], "dst": "86", "process_name": "com.weather.Weather", "process_id": "827", "log_time": "07-09 19:52:00.590", "message": "libcore.os.write(86) writing with tag 0x11 data[<?xml version='1.0' encoding='utf-8' standalone='yes' ?>.<map>.<string name=\"SMART_RATINGS_STATUS\">{]", "channel": "INTERNAL"}, {"src": ["Location", "GPS Location"], "dst": "52.94.233.123", "process_name": "com.weather.Weather", "process_id": "827", "log_time": "07-09 19:52:00.715", "message": "SSLOutputStream.write(52.94.233.123) received data with tag 0x11 data=[Action=SendMessage&MessageBody={\"deviceData\":{\"product\":\"yakju\",\"os\":\"Android  4.1.2\",\"application\":]", "channel": "HTTPS"}, {"src": ["Location", "GPS Location"], "dst": "52.94.233.123", "process_name": "com.weather.Weather", "process_id": "827", "log_time": "07-09 19:52:00.723", "message": "SSLOutputStream.write(52.94.233.123) received data with tag 0x11 data=[66666412353516,\"accuracy\":1,\"mobile\":false,\"fixType\":\"BACKGROUND\"},{\"alarmVolume\":71.42857360839844,]", "channel": "HTTPS"}, {"src": ["Location", "GPS Location"], "dst": "82", "process_name": "com.weather.Weather", "process_id": "827", "log_time": "07-09 19:52:03.488", "message": "libcore.os.write(82) writing with tag 0x11 data[<?xml version='1.0' encoding='utf-8' standalone='yes' ?>.<map>.<int name=\"airlock.userRandomNumber\" ]", "channel": "INTERNAL"}, {"src": ["Location", "GPS Location"], "dst": "82", "process_name": "com.weather.Weather", "process_id": "827", "log_time": "07-09 19:52:03.488", "message": "libcore.os.write(82) writing with tag 0x11 data[pollencast&quot;},&quot;description&quot;:&quot;Displayshealthinformation.&quot;},&quot;isON&quot;:t]", "channel": "INTERNAL"}, {"src": ["Location", "GPS Location"], "dst": "82", "process_name": "com.weather.Weather", "process_id": "827", "log_time": "07-09 19:52:03.496", "message": "libcore.os.write(82) writing with tag 0x11 data[&quot;:&quot;YES&quot;,&quot;feedbackButton&quot;:&quot;SEND FEEDBACK&quot;,&quot;negativeAnswerMess]", "channel": "INTERNAL"}, {"src": ["Location", "GPS Location"], "dst": "82", "process_name": "com.weather.Weather", "process_id": "827", "log_time": "07-09 19:52:03.504", "message": "libcore.os.write(82) writing with tag 0x11 data[headsupv2.Allergy&quot;,&quot;type&quot;:&quot;FEATURE&quot;,&quot;source&quot;:&quot;SERVER&quot;,&]", "channel": "INTERNAL"}, {"src": ["Location", "GPS Location"], "dst": "82", "process_name": "com.weather.Weather", "process_id": "827", "log_time": "07-09 19:52:03.512", "message": "libcore.os.write(82) writing with tag 0x11 data[FEATURE&quot;,&quot;source&quot;:&quot;SERVER&quot;,&quot;configurationStatuses&quot;:[],&quot;sendT]", "channel": "INTERNAL"}, {"src": ["Location", "GPS Location"], "dst": "82", "process_name": "com.weather.Weather", "process_id": "827", "log_time": "07-09 19:52:03.527", "message": "libcore.os.write(82) writing with tag 0x11 data[&quot;plat&quot;:&quot;wx_droid_phone&quot;,&quot;pos&quot;:&quot;top300&quot;,&quot;tile&quot;:&quo]", "channel": "INTERNAL"}, {"src": ["Location", "GPS Location"], "dst": "82", "process_name": "com.weather.Weather", "process_id": "827", "log_time": "07-09 19:52:03.535", "message": "libcore.os.write(82) writing with tag 0x11 data[&quot;:&quot;video.tv&quot;,&quot;adUnitSuffix&quot;:&quot;video\\/tv&quot;,&quot;parameters&quot;:{&]", "channel": "INTERNAL"}, {"src": ["Location", "GPS Location"], "dst": "82", "process_name": "com.weather.Weather", "process_id": "827", "log_time": "07-09 19:52:03.551", "message": "libcore.os.write(82) writing with tag 0x11 data[cust_params=cnd%3D%%CONDITION%%%26sev%3D%%SEVERE%%%26ftl%3D%%FTL%%%26hlzip%3D%%HLZIP%%%26tmp%3D%%TMP]", "channel": "INTERNAL"}, {"src": ["Location", "GPS Location"], "dst": "82", "process_name": "com.weather.Weather", "process_id": "827", "log_time": "07-09 19:52:03.566", "message": "libcore.os.write(82) writing with tag 0x11 data[airlock.direct.s3Path\">https://s3.amazonaws.com/airlockprod/PROD1/</string>.<string name=\"airlock.ca]", "channel": "INTERNAL"}, {"src": ["Location", "GPS Location"], "dst": "82", "process_name": "com.weather.Weather", "process_id": "827", "log_time": "07-09 19:52:03.613", "message": "libcore.os.write(82) writing with tag 0x11 data[<?xml version='1.0' encoding='utf-8' standalone='yes' ?>.<map>.<string name=\"inputFieldsForAnalytics]", "channel": "INTERNAL"}, {"src": ["Location", "GPS Location"], "dst": "82", "process_name": "com.weather.Weather", "process_id": "827", "log_time": "07-09 19:52:03.621", "message": "libcore.os.write(82) writing with tag 0x11 data[pollencast&quot;},&quot;description&quot;:&quot;Displayshealthinformation.&quot;},&quot;isON&quot;:t]", "channel": "INTERNAL"}, {"src": ["Location", "GPS Location"], "dst": "82", "process_name": "com.weather.Weather", "process_id": "827", "log_time": "07-09 19:52:03.637", "message": "libcore.os.write(82) writing with tag 0x11 data[&quot;:&quot;YES&quot;,&quot;feedbackButton&quot;:&quot;SEND FEEDBACK&quot;,&quot;negativeAnswerMess]", "channel": "INTERNAL"}, {"src": ["Location", "GPS Location"], "dst": "82", "process_name": "com.weather.Weather", "process_id": "827", "log_time": "07-09 19:52:03.644", "message": "libcore.os.write(82) writing with tag 0x11 data[headsupv2.Allergy&quot;,&quot;type&quot;:&quot;FEATURE&quot;,&quot;source&quot;:&quot;SERVER&quot;,&]", "channel": "INTERNAL"}, {"src": ["Location", "GPS Location"], "dst": "82", "process_name": "com.weather.Weather", "process_id": "827", "log_time": "07-09 19:52:03.652", "message": "libcore.os.write(82) writing with tag 0x11 data[FEATURE&quot;,&quot;source&quot;:&quot;SERVER&quot;,&quot;configurationStatuses&quot;:[],&quot;sendT]", "channel": "INTERNAL"}, {"src": ["Location", "GPS Location"], "dst": "82", "process_name": "com.weather.Weather", "process_id": "827", "log_time": "07-09 19:52:03.660", "message": "libcore.os.write(82) writing with tag 0x11 data[&quot;plat&quot;:&quot;wx_droid_phone&quot;,&quot;pos&quot;:&quot;top300&quot;,&quot;tile&quot;:&quo]", "channel": "INTERNAL"}, {"src": ["Location", "GPS Location"], "dst": "82", "process_name": "com.weather.Weather", "process_id": "827", "log_time": "07-09 19:52:03.668", "message": "libcore.os.write(82) writing with tag 0x11 data[&quot;:&quot;video.tv&quot;,&quot;adUnitSuffix&quot;:&quot;video\\/tv&quot;,&quot;parameters&quot;:{&]", "channel": "INTERNAL"}, {"src": ["Location", "GPS Location"], "dst": "82", "process_name": "com.weather.Weather", "process_id": "827", "log_time": "07-09 19:52:03.676", "message": "libcore.os.write(82) writing with tag 0x11 data[cust_params=cnd%3D%%CONDITION%%%26sev%3D%%SEVERE%%%26ftl%3D%%FTL%%%26hlzip%3D%%HLZIP%%%26tmp%3D%%TMP]", "channel": "INTERNAL"}, {"src": ["Location", "GPS Location"], "dst": "82", "process_name": "com.weather.Weather", "process_id": "827", "log_time": "07-09 19:52:03.676", "message": "libcore.os.write(82) writing with tag 0x11 data[ name=\"airlock.seasonId\">6f8cba0d-8e46-4c6b-8b70-9bac3cc5a085</string>.<string name=\"airlock.cached.]", "channel": "INTERNAL"}, {"src": ["Location", "GPS Location"], "dst": "82", "process_name": "com.weather.Weather", "process_id": "827", "log_time": "07-09 19:52:03.699", "message": "libcore.os.write(82) writing with tag 0x11 data[<?xml version='1.0' encoding='utf-8' standalone='yes' ?>.<map>.<int name=\"airlock.userRandomNumber\" ]", "channel": "INTERNAL"}, {"src": ["Location", "GPS Location"], "dst": "82", "process_name": "com.weather.Weather", "process_id": "827", "log_time": "07-09 19:52:03.707", "message": "libcore.os.write(82) writing with tag 0x11 data[pollencast&quot;},&quot;description&quot;:&quot;Displayshealthinformation.&quot;},&quot;isON&quot;:t]", "channel": "INTERNAL"}, {"src": ["Location", "GPS Location"], "dst": "82", "process_name": "com.weather.Weather", "process_id": "827", "log_time": "07-09 19:52:03.707", "message": "libcore.os.write(82) writing with tag 0x11 data[&quot;:&quot;YES&quot;,&quot;feedbackButton&quot;:&quot;SEND FEEDBACK&quot;,&quot;negativeAnswerMess]", "channel": "INTERNAL"}, {"src": ["Location", "GPS Location"], "dst": "82", "process_name": "com.weather.Weather", "process_id": "827", "log_time": "07-09 19:52:03.715", "message": "libcore.os.write(82) writing with tag 0x11 data[headsupv2.Allergy&quot;,&quot;type&quot;:&quot;FEATURE&quot;,&quot;source&quot;:&quot;SERVER&quot;,&]", "channel": "INTERNAL"}, {"src": ["Location", "GPS Location"], "dst": "82", "process_name": "com.weather.Weather", "process_id": "827", "log_time": "07-09 19:52:03.723", "message": "libcore.os.write(82) writing with tag 0x11 data[FEATURE&quot;,&quot;source&quot;:&quot;SERVER&quot;,&quot;configurationStatuses&quot;:[],&quot;sendT]", "channel": "INTERNAL"}, {"src": ["Location", "GPS Location"], "dst": "82", "process_name": "com.weather.Weather", "process_id": "827", "log_time": "07-09 19:52:03.730", "message": "libcore.os.write(82) writing with tag 0x11 data[&quot;plat&quot;:&quot;wx_droid_phone&quot;,&quot;pos&quot;:&quot;top300&quot;,&quot;tile&quot;:&quo]", "channel": "INTERNAL"}, {"src": ["Location", "GPS Location"], "dst": "82", "process_name": "com.weather.Weather", "process_id": "827", "log_time": "07-09 19:52:03.738", "message": "libcore.os.write(82) writing with tag 0x11 data[&quot;:&quot;video.tv&quot;,&quot;adUnitSuffix&quot;:&quot;video\\/tv&quot;,&quot;parameters&quot;:{&]", "channel": "INTERNAL"}, {"src": ["Location", "GPS Location"], "dst": "82", "process_name": "com.weather.Weather", "process_id": "827", "log_time": "07-09 19:52:03.746", "message": "libcore.os.write(82) writing with tag 0x11 data[cust_params=cnd%3D%%CONDITION%%%26sev%3D%%SEVERE%%%26ftl%3D%%FTL%%%26hlzip%3D%%HLZIP%%%26tmp%3D%%TMP]", "channel": "INTERNAL"}, {"src": ["Location", "GPS Location"], "dst": "82", "process_name": "com.weather.Weather", "process_id": "827", "log_time": "07-09 19:52:03.746", "message": "libcore.os.write(82) writing with tag 0x11 data[airlock.direct.s3Path\">https://s3.amazonaws.com/airlockprod/PROD1/</string>.<string name=\"airlock.ca]", "channel": "INTERNAL"}, {"src": ["Location", "GPS Location"], "dst": "82", "process_name": "com.weather.Weather", "process_id": "827", "log_time": "07-09 19:52:05.855", "message": "libcore.os.write(82) writing with tag 0x11 data[<?xml version='1.0' encoding='utf-8' standalone='yes' ?>.<map>.<int name=\"airlock.userRandomNumber\" ]", "channel": "INTERNAL"}, {"src": ["Location", "GPS Location"], "dst": "82", "process_name": "com.weather.Weather", "process_id": "827", "log_time": "07-09 19:52:05.863", "message": "libcore.os.write(82) writing with tag 0x11 data[pollencast&quot;},&quot;description&quot;:&quot;Displayshealthinformation.&quot;},&quot;isON&quot;:t]", "channel": "INTERNAL"}, {"src": ["Location", "GPS Location"], "dst": "82", "process_name": "com.weather.Weather", "process_id": "827", "log_time": "07-09 19:52:05.871", "message": "libcore.os.write(82) writing with tag 0x11 data[&quot;:&quot;YES&quot;,&quot;feedbackButton&quot;:&quot;SEND FEEDBACK&quot;,&quot;negativeAnswerMess]", "channel": "INTERNAL"}, {"src": ["Location", "GPS Location"], "dst": "82", "process_name": "com.weather.Weather", "process_id": "827", "log_time": "07-09 19:52:05.871", "message": "libcore.os.write(82) writing with tag 0x11 data[headsupv2.Allergy&quot;,&quot;type&quot;:&quot;FEATURE&quot;,&quot;source&quot;:&quot;SERVER&quot;,&]", "channel": "INTERNAL"}, {"src": ["Location", "GPS Location"], "dst": "82", "process_name": "com.weather.Weather", "process_id": "827", "log_time": "07-09 19:52:05.879", "message": "libcore.os.write(82) writing with tag 0x11 data[FEATURE&quot;,&quot;source&quot;:&quot;SERVER&quot;,&quot;configurationStatuses&quot;:[],&quot;sendT]", "channel": "INTERNAL"}, {"src": ["Location", "GPS Location"], "dst": "82", "process_name": "com.weather.Weather", "process_id": "827", "log_time": "07-09 19:52:05.887", "message": "libcore.os.write(82) writing with tag 0x11 data[&quot;plat&quot;:&quot;wx_droid_phone&quot;,&quot;pos&quot;:&quot;top300&quot;,&quot;tile&quot;:&quo]", "channel": "INTERNAL"}, {"src": ["Location", "GPS Location"], "dst": "82", "process_name": "com.weather.Weather", "process_id": "827", "log_time": "07-09 19:52:05.894", "message": "libcore.os.write(82) writing with tag 0x11 data[&quot;:&quot;video.tv&quot;,&quot;adUnitSuffix&quot;:&quot;video\\/tv&quot;,&quot;parameters&quot;:{&]", "channel": "INTERNAL"}, {"src": ["Location", "GPS Location"], "dst": "82", "process_name": "com.weather.Weather", "process_id": "827", "log_time": "07-09 19:52:05.902", "message": "libcore.os.write(82) writing with tag 0x11 data[cust_params=cnd%3D%%CONDITION%%%26sev%3D%%SEVERE%%%26ftl%3D%%FTL%%%26hlzip%3D%%HLZIP%%%26tmp%3D%%TMP]", "channel": "INTERNAL"}, {"src": ["Location", "GPS Location"], "dst": "82", "process_name": "com.weather.Weather", "process_id": "827", "log_time": "07-09 19:52:05.902", "message": "libcore.os.write(82) writing with tag 0x11 data[airlock.direct.s3Path\">https://s3.amazonaws.com/airlockprod/PROD1/</string>.<string name=\"airlock.ca]", "channel": "INTERNAL"}, {"src": ["Location", "GPS Location"], "dst": "82", "process_name": "com.weather.Weather", "process_id": "827", "log_time": "07-09 19:52:05.949", "message": "libcore.os.write(82) writing with tag 0x11 data[<?xml version='1.0' encoding='utf-8' standalone='yes' ?>.<map>.<string name=\"inputFieldsForAnalytics]", "channel": "INTERNAL"}, {"src": ["Location", "GPS Location"], "dst": "82", "process_name": "com.weather.Weather", "process_id": "827", "log_time": "07-09 19:52:05.957", "message": "libcore.os.write(82) writing with tag 0x11 data[pollencast&quot;},&quot;description&quot;:&quot;Displayshealthinformation.&quot;},&quot;isON&quot;:t]", "channel": "INTERNAL"}, {"src": ["Location", "GPS Location"], "dst": "82", "process_name": "com.weather.Weather", "process_id": "827", "log_time": "07-09 19:52:05.965", "message": "libcore.os.write(82) writing with tag 0x11 data[&quot;:&quot;YES&quot;,&quot;feedbackButton&quot;:&quot;SEND FEEDBACK&quot;,&quot;negativeAnswerMess]", "channel": "INTERNAL"}, {"src": ["Location", "GPS Location"], "dst": "82", "process_name": "com.weather.Weather", "process_id": "827", "log_time": "07-09 19:52:05.973", "message": "libcore.os.write(82) writing with tag 0x11 data[headsupv2.Allergy&quot;,&quot;type&quot;:&quot;FEATURE&quot;,&quot;source&quot;:&quot;SERVER&quot;,&]", "channel": "INTERNAL"}, {"src": ["Location", "GPS Location"], "dst": "82", "process_name": "com.weather.Weather", "process_id": "827", "log_time": "07-09 19:52:05.973", "message": "libcore.os.write(82) writing with tag 0x11 data[FEATURE&quot;,&quot;source&quot;:&quot;SERVER&quot;,&quot;configurationStatuses&quot;:[],&quot;sendT]", "channel": "INTERNAL"}, {"src": ["Location", "GPS Location"], "dst": "82", "process_name": "com.weather.Weather", "process_id": "827", "log_time": "07-09 19:52:05.980", "message": "libcore.os.write(82) writing with tag 0x11 data[&quot;plat&quot;:&quot;wx_droid_phone&quot;,&quot;pos&quot;:&quot;top300&quot;,&quot;tile&quot;:&quo]", "channel": "INTERNAL"}, {"src": ["Location", "GPS Location"], "dst": "82", "process_name": "com.weather.Weather", "process_id": "827", "log_time": "07-09 19:52:05.988", "message": "libcore.os.write(82) writing with tag 0x11 data[&quot;:&quot;video.tv&quot;,&quot;adUnitSuffix&quot;:&quot;video\\/tv&quot;,&quot;parameters&quot;:{&]", "channel": "INTERNAL"}, {"src": ["Location", "GPS Location"], "dst": "82", "process_name": "com.weather.Weather", "process_id": "827", "log_time": "07-09 19:52:05.996", "message": "libcore.os.write(82) writing with tag 0x11 data[cust_params=cnd%3D%%CONDITION%%%26sev%3D%%SEVERE%%%26ftl%3D%%FTL%%%26hlzip%3D%%HLZIP%%%26tmp%3D%%TMP]", "channel": "INTERNAL"}, {"src": ["Location", "GPS Location"], "dst": "82", "process_name": "com.weather.Weather", "process_id": "827", "log_time": "07-09 19:52:05.996", "message": "libcore.os.write(82) writing with tag 0x11 data[ name=\"airlock.seasonId\">6f8cba0d-8e46-4c6b-8b70-9bac3cc5a085</string>.<string name=\"airlock.cached.]", "channel": "INTERNAL"}]