{"domain": "cm.g.doubleclick.net", "post_body": "", "platform": "unknown", "referrer": "unknown", "uri": "/pixel?google_nid=turn1&google_cm&google_sc&google_hm=NDIyOTE4MTQ2MTg4NzA5Mzg1Mw==", "label": 1, "headers": {"host": "cm.g.doubleclick.net", "user-agent": "Mozilla/5.0 (X11; Ubuntu; Linux x86_64; rv:33.0) Gecko/20100101 Firefox/33.0", "accept": "image/png,image/*;q=0.8,*/*;q=0.5", "accept-language": "en-US,en;q=0.5", "accept-encoding": "gzip, deflate", "referer": "http://cdn.turn.com/server/ddc.htm?uid=4229181461887093853&mktid=736&mpid=&fpid=12&rnd=4244771610230226586&nu=y&sp=n&ctid=1&cyid=16", "cookie": "id=26a984cd978ee372||t=1425567869|et=730|cs=002213fd48897efede724209fe; _drt_=NO_DATA", "connection": "keep-alive"}, "timestamp": "2015-03-06_09-38-28-265483"}